<?xml version="1.0" encoding="UTF-8"?>
<result>
    <string>애니타임로또|-|36.3514617|127.3345399|대전 유성구 계룡로46번길 85|1</string>
    <string>대광슈퍼|031-391-6647|37.3710857|126.9339515|경기 군포시 고산로 679 미성프라자106호|1</string>
    <string>로또박사|031-853-0293|37.7495037|127.069431|경기 의정부시 신곡동 760-2번지 세명프라자1층|1</string>
    <string>로또스튜디오|043-216-3927|36.6665113|127.481471|충북 청주시 청원구 사뜸로 48-1 동성교회 1층|1</string>
    <string>썬마트|043-232-3015|36.6325577|127.4281202|충북 청주시 흥덕구 진재로23번길 25|1</string>
    <string>Let'sgo복권유통|063-246-4530|35.82815220000001|127.1647006|전북 전주시 덕진구 무삼지로 29|1</string>
    <string>불국사명당복권|054-743-3450|35.7144129|129.3239377|경북 경주시 산업로 3033|1</string>
    <string>로또방|055-237-4411|35.2492611|128.6683778|경남 창원시 의창구 봉곡로 81|1</string>
    <string>로또판매|02-3442-0070|37.50557|127.0583181|서울 강남구 삼성로86길 10 1층 삼성슈퍼|2</string>
    <string>만물|02-554-3636|37.5050143|127.0398871|서울 강남구 테헤란로37길 42|2</string>
    <string>로또복권판매|02-986-2306|37.630292|127.0236063|서울 강북구 미아동 217-2 미니스톱 내 위치함|2</string>
    <string>복권천국|02-2666-1339|37.5682177|126.8129502|서울 강서구 방화대로33길 66|2</string>
    <string>Today|-|37.5349372|127.0957088|서울 광진구 광나루로56길 85 테크노마트9층판매동24호|2</string>
    <string>로또복권|02-862-7908|37.4971668|126.888683|서울 구로구 구로중앙로24길 22-2 지1층|2</string>
    <string>대박복권방|02-893-4953|37.4650368|126.9036597|서울 금천구 독산로64길 18|2</string>
    <string>노다지 노원역점 복권방|02-937-8686|37.656184|127.0637347|서울 노원구 상계로 78,(상계동)|2</string>
    <string>GS25(중계동진)|02-934-0207|37.6504469|127.0774373|서울 노원구 중계동 364-23번지동진빌딩103|2</string>
    <string>일성|-|37.6395387|127.0375784|서울 도봉구 덕릉로57길 18 1층 일성식당 일부|2</string>
    <string>고대잉크복권방|02-3390-0398|37.5937758|127.0586458|서울 동대문구 이문로 76|2</string>
    <string>가로판매점|02-392-6588|37.5584944|126.9345627|서울 서대문구 신촌로 103,(창천동)|2</string>
    <string>가로판매점18호|02-312-5834|37.5586463|126.9459451|서울 서대문구 신촌역로 16 신촌가이아 주소앞 가판대 이전건|2</string>
    <string>CU 송파고분로점|02-422-0181|37.5067959|127.1156179|서울 송파구 백제고분로46길 43 오성빌딩|2</string>
    <string>가판대20호|02-409-7288|37.5003751|127.1110805|서울 송파구 송파대로 365 석촌농협앞가판대20호|2</string>
    <string>복권가판대|02-372-4396|37.5845548|126.8937086|서울 은평구 수색동 360번지|2</string>
    <string>프레야행운방|02-2048-1472|37.5624526|127.0164922|서울 중구 다산로36길 21|2</string>
    <string>두산타워앞로또판매점|02-2269-9626|37.5689316|127.0087977|서울 중구 을지로6가 18-12번지|2</string>
    <string>로또복권방|070-8285-9143|37.5649028|126.9902671|서울 중구 마른내로 21|2</string>
    <string>복권|070-8849-8958|37.5926999|127.0742542|서울 중랑구 망우로30길 8 105호|2</string>
    <string>로또판매점(바이더웨이)|051-583-8302|35.2465034|129.0908429|부산 금정구 구서동 415-2번지|2</string>
    <string>롯또(파워세일마트)|051-755-0749|35.1611463|129.1186539|부산 수영구 무학로 44-1 파워세일마트 내|2</string>
    <string>오렌지데이연산제일점|051-852-0037|35.1866535|129.082752|부산 연제구 반송로 12 CU마트내 별도부스|2</string>
    <string>황금어장|051-469-4853|35.1062569|129.0366472|부산 중구 중앙대로 96 흥우빌딩1층 나들가게편의점|2</string>
    <string>세븐로또(성당점)|053-621-6266|35.8385792|128.5526578|대구 달서구 성당동 392-55번지1층 세븐일레븐 내|2</string>
    <string>세븐일레븐 현풍대로점|053-617-7997|35.6905508|128.4450855|대구 달성군 비슬로 581 세븐일레븐현풍대로점|2</string>
    <string>다사복권방|053-000-0000|35.7902952|128.470664|대구 달성군 옥포면 간경리 848번지 FC24편의점 내|2</string>
    <string>CU(구월프랜드점)|032-471-5418|37.4472014|126.7075978|인천 남동구 구월동 1191-10번지|2</string>
    <string>우리복권|032-422-5008|37.4016667|126.7230556|인천 남동구 논고개로123번길 17 아이플렉스 102호 CU편의점 내|2</string>
    <string>행운마트|032-429-3278|37.4717542|126.6953548|인천 부평구 배곶남로9번길 4|2</string>
    <string>복권마을|032-502-4865|37.5158745|126.7045185|인천 부평구 마장로 424|2</string>
    <string>신일사|032-882-2089|37.4685237|126.6416009|인천 중구 참외전로 244-2|2</string>
    <string>갤러리로또|032-212-6422|37.4577086|126.630451|인천 중구 신흥동3가 7-308번지 씨팰리스오피스텔104호편의점내|2</string>
    <string>버스매표소 복권판매소|032-761-5555|37.4703324|126.6279111|인천 중구 우현로 69 중앙로지하상가 163호|2</string>
    <string>씨유 대전원내점|042-543-8949|36.3001213|127.3196236|대전 유성구 원내로 35|2</string>
    <string>탑25시복권방|052-263-5008|35.5689934|129.1120895|울산 울주군 언양읍 서부리 235-10번지 초대박TOP로또복권방내|2</string>
    <string>탑25시복권방|052-263-5008|35.5689934|129.1120895|울산 울주군 언양읍 서부리 235-10번지 초대박TOP로또복권방내|2</string>
    <string>땡큐25(철산점)|02-2625-6770|37.4754606|126.8671774|경기 광명시 철산동 264번지 로데오빌딩103호|2</string>
    <string>미소로또|-|37.6025025|127.1545601|경기 남양주시 가운로1길 17 마이라이프 오피스텔|2</string>
    <string>GS25(야탑프리아)|031-703-6525|37.4095417|127.1305786|경기 성남시 분당구 야탑동 514-4번지 프리아오프스텔101호|2</string>
    <string>시흥장곡점로또판매|031-317-8079|37.3780476|126.7843938|경기 시흥시 장곡동 817-3번지 1층|2</string>
    <string>행운슈퍼|070-4112-4851|37.4047358|126.9195061|경기 안양시 만안구 만안로 280|2</string>
    <string>버스표가판점|031-421-6455|37.3982565|126.9775888|경기 안양시 동안구 흥안대로 498-2|2</string>
    <string>광동서점|031-874-0631|37.7548975|127.0376032|경기 의정부시 서부로 693|2</string>
    <string>세이브마트|031-847-2480|37.7563073|127.0763036|경기 의정부시 금오로 100|2</string>
    <string>로또나라|-|37.7001427|126.6839756|경기 파주시 자유로 2212|2</string>
    <string>천하명당|031-542-8480|37.8284495|127.1448254|경기 포천시 송우로 38|2</string>
    <string>대박로또|041-841-4777|36.5504752|126.9525251|충남 공주시 유구읍 중앙2길 70 1층|2</string>
    <string>신방복권|041-552-7496|36.7886648|127.120839|충남 천안시 동남구 신촌로 19 101호|2</string>
    <string>한아름매점|041-641-4701|36.5032027|126.625575|충남 홍성군 광천로 330|2</string>
    <string>드림복권|063-834-8808|35.9569751|126.9799335|전북 익산시 무왕로20길 20-2|2</string>
    <string>훼미리마트 우아대로점|063-246-2949|35.8354802|127.1673533|전북 전주시 덕진구 건산로 276,(우아동2가)|2</string>
    <string>부자복권방|-|35.8323887|127.1030887|전북 전주시 완산구 서곡4길 45-4|2</string>
    <string>종합복권방|061-536-8161|34.5707411|126.6109401|전남 해남군 해남로 34 종합복권방편의점|2</string>
    <string>영일상사|-|36.0160803|129.3591533|경북 포항시 남구 상도동 18-103번지|2</string>
    <string>CU(두호점)|054-241-3036|36.0602925|129.3787478|경북 포항시 북구 두호동 1034-13번지|2</string>
    <string>로터리편의마트|054-247-2990|36.0407397|129.3672381|경북 포항시 북구 서동로 85 육거리|2</string>
    <string>로또|055-674-3774|34.97606950000001|128.3254553|경남 고성군 고성읍 동외로167번길 11|2</string>
    <string>삼삼마트|055-742-5632|35.1951449|128.0756609|경남 진주시 진주대로 1165-1|2</string>
    <string>육교상회|055-241-7866|35.2201104|128.5868497|경남 창원시 마산합포구 산호동 10-21번지|2</string>
    <string>창원병원앞매표소|055-266-2460|35.2187449|128.6724378|경남 창원시 성산구 중앙동 104-1번지 가판|2</string>
    <string>잉크폴|055-546-2814|35.1565304|128.6997967|경남 창원시 진해구 진해대로776번길 15 501동 102호|2</string>
    <string>온세계전자|064-796-4565|33.4153051|126.2652987|제주 제주시 한림로12길 1-1|2</string>
</result>
