<?xml version="1.0" encoding="UTF-8"?>
<result>
    <string>베네시티앞가판|02-473-1128|37.540481|127.1249608|서울 강동구 올림픽로 664 대우베네시티cafe7gram앞|1</string>
    <string>대박복권방|02-2681-1606|37.49166779999999|126.8548187|서울 구로구 개봉로17길 18|1</string>
    <string>복권명당|02-826-7209|37.4980745|126.9292014|서울 동작구 국사봉길 26|1</string>
    <string>SK 복권방|032-501-5633|37.4763739|126.7140248|인천 미추홀구 용정공원로 33 인천SKSkyVIEW 상가 A-2동 1층 104호|1</string>
    <string>로또판매점|-|37.643816|126.6647441|경기 김포시 김포한강2로 208 고창마을케이시시스위첸아파트 스웨첸아파트상가1동101호씨유kcc점|1</string>
    <string>슈퍼맨편의점|033-647-5211|37.7558584|128.8977235|강원 강릉시 경강로 2113 꽃사슴복권방|1</string>
    <string>행운복권|043-652-1088|37.1422871|128.2086339|충북 제천시 명륜로 67 1층|1</string>
    <string>후레쉬마트|02-426-7999|37.5460515|127.1722204|서울 강동구 천호대로 1476|2</string>
    <string>만조복권|-|37.5080791|126.8514633|서울 구로구 고척로 235 1충(고척동)|2</string>
    <string>대박복권방|02-893-4953|37.4650368|126.9036597|서울 금천구 독산로64길 18|2</string>
    <string>인터넷 복권판매사이트|02-1588-6450|0|0|동행복권(dhlottery.co.kr)|2</string>
    <string>오케이상사|02-6282-2312|37.5038594|127.0033439|서울 서초구 신반포로 176 센트럴시티내100호매점|2</string>
    <string>인터넷 복권판매사이트|02-1588-6450|0|0|동행복권(dhlottery.co.kr)|2</string>
    <string>인터넷 복권판매사이트|02-1588-6450|0|0|동행복권(dhlottery.co.kr)|2</string>
    <string>대원슈퍼|02-918-0457|37.6041902|127.0376727|서울 성북구 오패산로 22|2</string>
    <string>토큰판매소|02-472-5738|37.5366547|127.1223464|서울 송파구 바람드리길 62|2</string>
    <string>해피데이마트|02-409-9792|37.4890152|127.1246681|서울 송파구 동남로6길 14 1층|2</string>
    <string>농가마트|02-2646-5470|37.5199372|126.8532703|서울 양천구 중앙로 264 1층|2</string>
    <string>제이복권방|02-764-3232|37.5712637|127.0028305|서울 종로구 종로 225-1 평창빌딩 1층 103호|2</string>
    <string>갤러리마트|02-492-8251|37.5808867|127.0877217|서울 중랑구 사가정로 387|2</string>
    <string>천하명당초량점|051-465-9497|35.1168809|129.0401224|부산 동구 중앙대로221번길 3|2</string>
    <string>사이버정보통신|051-852-8910|35.1741035|129.0702837|부산 부산진구 동평로 411 백조상가동103-1호|2</string>
    <string>복권방|051-265-9677|35.0809726|128.9681976|부산 사하구 장림번영로 25|2</string>
    <string>무지개상점|-|35.1741147|129.1735879|부산 해운대구 좌동로91번길 45|2</string>
    <string>일등복권편의점|053-522-6808|35.8422121|128.5362156|대구 달서구 대명천로 220 1층|2</string>
    <string>서재강변로또|053-591-3747|35.8786863|128.4969175|대구 달성군 다사읍 서재로 172,(서재리)|2</string>
    <string>명가로또점|-|35.8736476|128.5713949|대구 서구 달서로 130 제12호,제8호|2</string>
    <string>세진전자통신|053-566-4466|35.871901|128.5552024|대구 서구 서대구로 156|2</string>
    <string>행운마트|053-746-5999|35.8635354|128.6439801|대구 수성구 만촌로 51,(만촌동)|2</string>
    <string>메트로센터점|053-254-3485|35.8655197|128.59339|대구 중구 달구벌대로 지하 2100 메트로센터C412호|2</string>
    <string>복권판매점(로또횡재)|053-428-3311|35.8682868|128.6062906|대구 중구 국채보상로140길 12|2</string>
    <string>복권명가|032-463-0645|37.4463351|126.7346224|인천 남동구 장승로 13 1층 101호|2</string>
    <string>노다지복권방|032-261-2149|37.44298879999999|126.6650313|인천 미추홀구 한나루로 400 학익시장 외7필지125호|2</string>
    <string>명품 복권|-|37.4660365|126.6591637|인천 미추홀구 경인로 148-2|2</string>
    <string>로또복권|032-571-3209|37.5153712|126.6684957|인천 서구 염곡로 343-4|2</string>
    <string>모아드림복권방|062-943-7778|35.1522943|126.7931986|광주 광산구 소촌로 90 1층 복권방|2</string>
    <string>커피로또|-|36.4442355|127.4260061|대전 대덕구 석봉로38번길 67|2</string>
    <string>후생사제3매장|042-623-2525|36.349671|127.4469756|대전 동구 비래서로42번길 105,(가양동)|2</string>
    <string>로또복권벽산블루밍|042-535-9100|36.3332792|127.3816934|대전 서구 갈마로 262|2</string>
    <string>태양마트|042-477-6236|36.3736787|127.3173777|대전 유성구 노은로 157 골드프라자 106호|2</string>
    <string>종점할아버지|052-297-8010|35.6284119|129.3538074|울산 북구 동대5길 18 102호|2</string>
    <string>여기로또|-|35.6079284|129.3710963|울산 북구 송정14길 8 1층102호|2</string>
    <string>복권방(행운열차)|052-222-3382|35.5630942|129.2672737|울산 중구 다운로 114|2</string>
    <string>명동슈퍼|02-2615-3382|37.4739663|126.8693507|경기 광명시 디지털로 17 1동 107호(철산동, (주)티오티비 오렌지타운)|2</string>
    <string>로또판매 김포운양점|-|37.655878|126.683013|경기 김포시 김포한강11로 276 풍경마을반도유보라아파트 718동 지1층 101호,풍경마을반도유보라아파트|2</string>
    <string>로또편의점|-|37.6426035|126.6787744|경기 김포시 김포한강11로 288-32 골든스퀘어101호|2</string>
    <string>베스트2|-|37.4416093|127.142568|경기 성남시 수정구 산성대로 지하 204-2 A동 다열 9호(신흥동, 성남중앙지하도상가)|2</string>
    <string>21세기복권나라|031-745-1286|37.4335461|127.158837|경기 성남시 중원구 둔촌대로 379|2</string>
    <string>천하명당복권방|031-246-1266|37.2666098|127.0018504|경기 수원시 팔달구 매산로 2|2</string>
    <string>좋은 날|-|37.2832735|127.0339964|경기 수원시 팔달구 팔달문로 165 104호(우만동)|2</string>
    <string>드림메드|031-405-1743|37.3333685|126.8508856|경기 안산시 상록구 월피로 56 101호|2</string>
    <string>종합복권나라|031-774-7950|37.5449011|127.3205058|경기 양평군 북한강로 12 1층|2</string>
    <string>고덕로또복권|031-667-4306|37.043909|127.013414|경기 평택시 고덕여염12길 37 1층 101호|2</string>
    <string>천우로또복권방|031-357-9003|37.2111441|126.7332036|경기 화성시 사강로 172|2</string>
    <string>화랑로또판매점|031-354-3554|37.1674276|126.8956839|경기 화성시 푸른들판로 660 정수상가|2</string>
    <string>올인(allin)|031-353-5311|37.1352679|126.9106117|경기 화성시 3.1만세로 1147|2</string>
    <string>일등 복권방|-|37.7574235|128.8874878|강원 강릉시 강릉대로 155|2</string>
    <string>나눔로또하이원점|033-592-1100|37.2272023|128.8160702|강원 정선군 사북중앙로 13 로또판매점|2</string>
    <string>407억당첨가판점|033-256-4710|37.8791912|127.7266262|강원 춘천시 중앙로 65 국민은행앞 가판|2</string>
    <string>콕콕로또명당옥천점|-|36.2966907|127.5962688|충북 옥천군 서대구일로 265-19 옥천하휴게소|2</string>
    <string>혁신대박|-|36.8788156|127.6270843|충북 음성군 원중로 1434 103호(에스타워)|2</string>
    <string>대박복권판매점|043-854-2635|36.9688433|127.9149756|충북 충주시 탄금대로 14,(문화동)|2</string>
    <string>로또복권방|041-881-1811|36.4553848|127.1335798|충남 공주시 우금티로 789-1,(옥룡동)|2</string>
    <string>논산복권방|041-734-7864|36.20392210000001|127.0897047|충남 논산시 계백로 1016|2</string>
    <string>토토복권방|070-8814-3521|36.7686634|126.4630622|충남 서산시 동서1로 63|2</string>
    <string>행운마트|041-532-7997|36.8818957|126.9107297|충남 아산시 서해로 654|2</string>
    <string>달성로또복권판매소|041-545-6192|36.7807774|127.0079053|충남 아산시 온천대로 1531|2</string>
    <string>플러스24쌍용본점|041-578-1066|36.7971961|127.1181367|충남 천안시 서북구 월봉로 74|2</string>
    <string>로또복권|044-866-0950|36.6043027|127.2985252|세종 조치원읍 조치원로 3-1,(원리)|2</string>
    <string>월야하나로복권|061-323-7751|35.179503|126.6272229|전남 함평군 밀재로 1512 1층|2</string>
    <string>레인보우|-|35.842674|128.719836|경북 경산시 성동로 16 101호|2</string>
    <string>텀브커피왜관점 로또명당|054-977-9909|35.6469805|128.7534183|경북 칠곡군 중앙로 95 1층 커피&amp;로또명당|2</string>
    <string>행운로또|-|35.2007119|128.8154057|경남 김해시 장유로301번길 12 복권판매점|2</string>
    <string>씨스페이스사천큰마트점|055-852-8552|35.0830466|128.0870511|경남 사천시 사천읍 평화2길 22|2</string>
    <string>제일복권|-|35.3355774|129.0279684|경남 양산시 양산역2길 7 대상골드타워 103호 복권판매점|2</string>
    <string>복권파는집|055-256-7746|35.2401941|128.5836421|경남 창원시 마산회원구 3·15대로 765|2</string>
    <string>잉크와복권|055-255-1030|35.2786081|128.6862473|경남 창원시 의창구 의창대로 875|2</string>
</result>
