<?xml version="1.0" encoding="UTF-8"?>
<result>
    <string>가로가판대제57호(구)|02-319-2598|37.5628771|126.977058|서울 중구 세종대로14길 6-2|1</string>
    <string>복권마트|-|35.1768336|126.8772275|광주 북구 북문대로 89 벽산메가시티상가 101동 116호|1</string>
    <string>운천 대박 복권방|031-534-6450|38.0895109|127.2745195|경기 포천시 영북면 영북로 171-1,(운천리)|1</string>
    <string>팡팡복권마트.잡화슈퍼|063-251-7764|35.8343875|127.1333902|전북 전주시 덕진구 가리내로 26|1</string>
    <string>후레쉬마트|02-426-7999|37.5460515|127.1722204|서울 강동구 천호대로 1476|2</string>
    <string>진로베스토아 편의점|02-878-0678|37.4682459|126.9375403|서울 관악구 신림9동 247-2|2</string>
    <string>복권방|02-864-8688|37.4939155|126.8826258|서울 구로구 구로동 409-80 1층|2</string>
    <string>로또|02-956-1463|37.6693897|127.0464436|서울 도봉구 마들로 664|2</string>
    <string>네잎클로버복권방|02-2212-6881|37.5785383|127.0703504|서울 동대문구 사가정로 230|2</string>
    <string>가판 뚝섬에스콰이야|02-497-9911|37.5476525|127.0447476|서울 성동구 왕십리로 114|2</string>
    <string>로또복권판매|-|37.5171239|126.9081027|서울 영등포구 영등포동3가 10-1|2</string>
    <string>GS25(종로사직)|02-725-8425|37.5777593|126.9717463|서울 종로구 체부동 37-1번지|2</string>
    <string>복권방휴게소|051-819-4567|35.1585604|129.0582295|부산 부산진구 부전동 259-18|2</string>
    <string>만구수산유통|051-253-3573|35.0926611|129.0244828|부산 서구 남부민동 685 현대타운1층 86호|2</string>
    <string>훼미리마트(참미소점)|053-573-9559|35.8472922|128.5375727|대구 달서구 감삼동 170-7|2</string>
    <string>복권나라|053-249-5288|35.8604787|128.5461354|대구 서구 당산로 273,(내당동)|2</string>
    <string>GS25(대전송촌)|042-632-5503|36.3649336|127.43885|대전 대덕구 송촌동 456-9|2</string>
    <string>대승로또|070-8741-7115|36.30749|127.3754588|대전 서구 복수동 대전 서구 복수동 274-13|2</string>
    <string>영화유통 (1등복권방)|052-269-9851|35.5338415|129.3221564|울산 남구 신정로 19 삼성아파트 상가 204-101|2</string>
    <string>복권명당집시장점|070-8677-5100|37.8919963|127.0529807|경기 동두천시 지행동 718-3 송내프라자 103|2</string>
    <string>돼지복권|031-754-1268|37.4587324|127.126875|경기 성남시 수정구 복정동 복정동 686-3|2</string>
    <string>행운복권방|031-291-1056|37.2402801|126.9658243|경기 수원시 권선구 오목천동 오목천동 431-1 로뎀프라자|2</string>
    <string>바이웨이시흥메가점|031-498-7224|37.3544729|126.7233892|경기 시흥시 정왕대로 64 메가쇼핑몰1층123호|2</string>
    <string>천마 매표소|-|37.7632153|126.7829677|경기 시흥시 시청로 100 002호|2</string>
    <string>GS25(안산원곡)|031-401-7782|37.3262799|126.8000589|경기 안산시 단원구 원곡동 원곡동 838-105|2</string>
    <string>월드슈퍼|031-407-7297|37.3087429|126.8692689|경기 안산시 상록구 웃말1안길 48 1층|2</string>
    <string>로또 명당 가두판매점|031-388-4427|37.3873596|126.9447542|경기 안양시 동안구 경수대로 848-2 동안구가로판매대2005-00065|2</string>
    <string>천하명당 복권방|031-453-0915|37.3485614|126.9740871|경기 의왕시 경수대로 248 보왕빌딩|2</string>
    <string>코사마트역전점|031-655-3407|36.9919767|127.0872208|경기 평택시 중앙2로 1|2</string>
    <string>훼미리마트(제천고암)|043-644-5222|37.1577812|128.2146852|충북 제천시 고암로 69 1층 CU편의점|2</string>
    <string>로또 복권방|043-298-5001|36.6303889|127.4743848|충북 청주시 서원구 호국로25번길 1|2</string>
    <string>복권명당황남|054-749-2924|35.827264|129.2099189|경북 경주시 포석로 966|2</string>
</result>
