<?xml version="1.0" encoding="UTF-8"?>
<result>
    <string>소리창고|02-3665-3021|37.5528468|126.8367329|서울 강서구 강서로 306|1</string>
    <string>-|-|35.23122900000001|129.0155998|부산 북구 금곡대로 270 상가동 110호|1</string>
    <string>알리바이|062-961-7142|35.1853131|126.8366684|광주 광산구 수등로 253 1층 알리바이|1</string>
    <string>로또복권|042-626-8414|36.3415331|127.4484167|대전 동구 자양동 198-17|1</string>
    <string>가판대|031-441-3865|37.39279|126.9259848|경기 안양시 만안구 안양동 456-2|1</string>
    <string>대박나라복권방|041-542-8973|36.7773321|126.9344175|충남 아산시 서부남로 868|1</string>
    <string>행운복권방(감포)|054-741-8407|35.8066302|129.5023164|경북 경주시 감포로 141|1</string>
    <string>소리창고|02-3665-3021|37.5528468|126.8367329|서울 강서구 강서로 306|2</string>
    <string>로또|02-3661-9301|37.5633242|126.8524946|서울 강서구 가양동 1480-8102호|2</string>
    <string>소문난복권명당|02-966-6372|37.6068799|127.0608376|서울 성북구 돌곶이로 29|2</string>
    <string>복권나라|02-414-0877|37.5003207|127.0950102|서울 송파구 백제고분로32길 23 1층복권나라|2</string>
    <string>클린마트|02-388-8318|37.6009412|126.9319959|서울 은평구 응암동 61-53 1층|2</string>
    <string>-|051-256-2510|35.0983004|129.0323252|부산 중구 구덕로34번길 4 가판집|2</string>
    <string>훼미리마트(입석강변점)|053-985-8254|35.8902065|128.6464301|대구 동구 입석동 933-2|2</string>
    <string>진슈퍼|053-764-8856|35.872694|128.6472767|대구 수성구 무열로 161 1층 복권판매점|2</string>
    <string>로또명당|032-422-6928|37.4510549|126.6882778|인천 미추홀구 인주대로 463|2</string>
    <string>GS25(동암북부)|032-423-1688|37.4717209|126.7023158|인천 부평구 십정동 402-58|2</string>
    <string>노다지복권방|032-819-6338|37.4077941|126.6720117|인천 연수구 앵고개로 256|2</string>
    <string>현대슈퍼|062-371-3958|35.1505407|126.8573076|광주 서구 상무대로 871|2</string>
    <string>복권나라|031-977-8737|37.6850482|126.7745935|경기 고양시 일산서구 원일로 114|2</string>
    <string>로또복권|-|37.458865|126.8821551|경기 광명시 금당로 36 8단지종합상가공유지|2</string>
    <string>슈퍼복권|031-564-9695|37.597107|127.1452197|경기 구리시 검배로 55 하이스트빌|2</string>
    <string>우리복권방|031-552-0864|37.600803|127.1343373|경기 구리시 경춘로 171,(교문동)|2</string>
    <string>으뜸복권방|070-8815-1822|37.3746488|127.1182617|경기 성남시 분당구 성남대로 151 엠코헤리츠 1층110호|2</string>
    <string>로또슈퍼|031-502-6700|37.3066198|126.8460914|경기 안산시 상록구 광덕1로 326 102호|2</string>
    <string>노다지복권방|031-487-3244|37.3323537|126.827175|경기 안산시 단원구 와동로 17 103호|2</string>
    <string>천하명당복권방|031-656-6116|36.9994573|127.0817745|경기 평택시 세교상가1길 68|2</string>
    <string>로또복권|033-748-1209|37.3316445|127.9516995|강원 원주시 개운동 444-9|2</string>
    <string>운수대통복권방|033-264-4478|37.85892|127.7426069|강원 춘천시 후석로 52|2</string>
    <string>천하제일복권방|043-272-4697|36.6277392|127.4757736|충북 청주시 서원구 매봉로 208 삼호아파트 삼호상가1-105|2</string>
    <string>로또BANK|041-858-7894|36.4734432|127.1374283|충남 공주시 공주대학로 95,(신관동)|2</string>
    <string>팡팡복권마트.잡화슈퍼|063-251-7764|35.8343875|127.1333902|전북 전주시 덕진구 가리내로 26|2</string>
    <string>플러스하나|061-745-8784|34.9330803|127.4894883|전남 순천시 우석로 49 플러스하나|2</string>
    <string>GMART|054-457-8488|36.1299943|128.3290682|경북 구미시 구미중앙로 57-3|2</string>
    <string>모아편의점|055-638-4068|35.1016294|128.4823385|경남 거제시 신현읍 고현리 96-1|2</string>
    <string>해피복권|055-242-0645|35.1755399|128.5623236|경남 창원시 마산합포구 가포로 98 1층 CU편의점 내|2</string>
    <string>북마산복권전문점|055-244-3626|35.2158006|128.5708622|경남 창원시 마산합포구 북성로 98|2</string>
    <string>목화휴게소|055-835-2780|35.0016472|128.0540468|경남 사천시 사천대로 912|2</string>
    <string>GS25(창원코아)|055-264-7841|35.2262676|128.6780244|경남 창원시 중앙동 84-1|2</string>
</result>
