<?xml version="1.0" encoding="UTF-8"?>
<result>
    <string>캐논종합|02-6733-8949|37.5334283|126.96217|서울 용산구 청파로 101 나진10동가125호|1</string>
    <string>부일카서비스|051-637-7747|35.1400577|129.0630673|부산 동구 자성로133번길 35|1</string>
    <string>로또복권방|031-945-2695|37.7660365|126.7682418|경기 파주시 금촌동 374-11|1</string>
    <string>스파|02-951-6465|37.6639381|127.0568063|서울 노원구 동일로 1493 상계주공아파트(10단지) 주공10단지종합상가111|2</string>
    <string>삼호복권|02-990-3553|37.6467349|127.0332406|서울 도봉구 도봉로 457|2</string>
    <string>GS25(사당역)|02-3473-2245|37.4771632|126.979833|서울 동작구 사당동 1044-37|2</string>
    <string>-|02-593-6553|37.4908721|126.9908902|서울 서초구 방배동 812-23|2</string>
    <string>배임|02-749-0108|37.5262328|127.0006426|서울 용산구 보광로 19 1층|2</string>
    <string>다우리상사|02-735-0733|37.5795286|126.9710971|서울 종로구 통인동 141-2|2</string>
    <string>하나열쇠|051-627-4088|35.1162954|129.1112894|부산 남구 용호로 179|2</string>
    <string>오렌지데이가야점|-|35.1537305|129.0366752|부산 부산진구 대학로 20-1 1층 복권방|2</string>
    <string>24시슈퍼|032-765-3023|37.477991|126.6328733|인천 동구 송현동 72-220|2</string>
    <string>복권방|032-523-0645|37.4939157|126.7351148|인천 부평구 부개동 131-11|2</string>
    <string>GS25(신공항)|032-752-1265|37.4722539|126.4688958|인천 중구 운서동 2790-1|2</string>
    <string>CU(상무중흥점)|062-372-7356|35.1545323|126.8478142|광주 서구 치평동 1184-2상무골든타운107 108호|2</string>
    <string>행운노다지복권방|042-535-8695|36.3380471|127.3843738|대전 서구 괴정동 78-1다세대주택 1층|2</string>
    <string>대광광고사|042-936-7878|36.4338189|127.3850604|대전 유성구 구즉로 54|2</string>
    <string>현대25편의점|070-4414-0789|37.6930774|126.7468612|경기 고양시 일산서구 미래로 164|2</string>
    <string>CU(원종깨비점)|032-675-2997|37.5238786|126.8052171|경기 부천시 오정구 원종동 280-91F|2</string>
    <string>성진마트|032-678-3224|37.5169586|126.7793046|경기 부천시 수도로 123,(내동)|2</string>
    <string>싼타슈퍼|031-433-3667|37.34552559999999|126.7473934|경기 시흥시 군서마을로 42|2</string>
    <string>복권마을|031-457-1571|37.3716109|126.9574408|경기 안양시 동안구 경수대로 547|2</string>
    <string>로또복권방|031-949-5587|37.7595556|126.7774135|경기 파주시 중앙로 263|2</string>
    <string>서울복권|033-647-3555|37.76355|128.8771875|강원 강릉시 솔올로5번길 52 1층 4호 복권판매점|2</string>
    <string>드림24|043-298-5001|36.6303889|127.4743848|충북 청주시 서원구 호국로25번길 1|2</string>
    <string>굿타임24아산석정점(구드림통신)|041-549-7011|36.8013196|127.0076258|충남 아산시 충무로 230|2</string>
    <string>청룡마트|070-8825-9937|36.7973858|127.1541779|충남 천안시 동남구 풍세로 1010-31 현대아파트상가B-102호|2</string>
    <string>운수대통복권방|041-554-1259|36.8004635|127.1492774|충남 천안시 동남구 대흥로 122 중앙시장 입구|2</string>
    <string>애니타임24(해신점)|063-445-0668|35.97009389999999|126.7189937|전북 군산시 문화로 119|2</string>
    <string>종합복권방|061-536-8161|34.5707411|126.6109401|전남 해남군 해남로 34 종합복권방편의점|2</string>
    <string>행운의집제1호점|054-843-5511|36.5651334|128.7333165|경북 안동시 영가로 24|2</string>
    <string>남부로또점|054-0000-0000|36.0100605|129.3616589|경북 포항시 남구 희망대로 811-1|2</string>
    <string>씨유고현점|055-635-2138|34.8827757|128.6257416|경남 거제시 거제중앙로 1841|2</string>
    <string>목화휴게소|055-835-2780|35.0016472|128.0540468|경남 사천시 사천대로 912|2</string>
</result>
