<?xml version="1.0" encoding="UTF-8"?>
<result>
    <string>GS25(압구정역)|02-549-3196|37.5254222|127.0275587|서울 강남구 신사동 577-12동헌빌딩1층|1</string>
    <string>세븐일레븐부산온천장역점|051-513-9147|35.2135235|129.0801377|부산 동래구 중앙대로 1520 북쪽출구 빵집|1</string>
    <string>복권백화점|031-943-7477|37.763607|126.7699255|경기 파주시 평화로 70|1</string>
    <string>행운예감|043-848-6007|36.97338360000001|127.9233033|충북 충주시 국원대로 5 1층|1</string>
    <string>둔포로또판매점|-|36.897134|127.0353143|충남 아산시 충무로 1810 둔포로또판매점|1</string>
    <string>CU(구미원평점)|054-458-5720|36.1257251|128.3447059|경북 구미시 송원서로8길 4|1</string>
    <string>영화복권방|055-339-8295|35.1774872|128.8021214|경남 김해시 덕정로 158 복권판매점|1</string>
    <string>일등복권방|064-783-1231|33.450195|126.9145044|제주 서귀포시 성산읍 고성리 1197-8|1</string>
    <string>가로판매점|02-985-3859|37.6133612|127.0295624|서울 강북구 송천동 60-4|2</string>
    <string>하나로슈퍼|02-964-8348|37.5827189|127.0388221|서울 동대문구 고산자로 484|2</string>
    <string>복권천국방|02-337-3259|37.5541923|126.9123721|서울 마포구 동교로 92 1층|2</string>
    <string>영광정보통신|02-911-5016|37.6026597|127.0424818|서울 성북구 화랑로 92 1층 우측1호|2</string>
    <string>ANY25|02-766-0409|37.5745964|126.9972785|서울 종로구 창경궁로 137 1층|2</string>
    <string>기장슈퍼|051-722-1187|35.2439|129.2165295|부산 기장군 기장읍 차성동로 69|2</string>
    <string>현아상회|051-623-6408|35.1197075|129.1128179|부산 남구 동명로145번길 3|2</string>
    <string>포시즌24시편의점로또|070-5227-1696|35.1649248|128.9794316|부산 사상구 광장로21번길 46|2</string>
    <string>신풍|051-203-4700|35.0942111|128.9598686|부산 사하구 하신번영로 127|2</string>
    <string>세진전자통신|053-566-4466|35.871901|128.5552024|대구 서구 서대구로 156,(평리동)|2</string>
    <string>거봉마트(원고개시장)|053-561-9393|35.8792752|128.5672612|대구 서구 북비산로 310,(평리동)|2</string>
    <string>씨엔에스|053-341-8778|35.8849085|128.5562446|대구 서구 비산동 1840-1|2</string>
    <string>로또명당|032-422-6928|37.4510549|126.6882778|인천 미추홀구 인주대로 463|2</string>
    <string>복권전문점|032-502-7960|37.5037948|126.7151051|인천 부평구 원적로 437|2</string>
    <string>CU(연안비취점)|032-882-8825|37.4535347|126.6057416|인천 중구 항동7가 27-131|2</string>
    <string>파워마트 복권나라|-|35.1915584|126.8833594|광주 북구 서하로 117 101호 (매곡동)|2</string>
    <string>연화네마트|-|35.2081871|126.8786916|광주 북구 양산택지로 17|2</string>
    <string>뉴스코복권|062-430-4080|35.1532436|126.8666743|광주 서구 쌍촌동 952-23|2</string>
    <string>GS25(대전터미널)|042-638-2050|36.3519703|127.4364195|대전 동구 용전동 63-11|2</string>
    <string>행운로또복권|052-282-4056|35.5553377|129.3349052|울산 중구 학성동 153-2|2</string>
    <string>버스표판매소|031-978-0261|37.634643|126.832633|경기 고양시 덕양구 화정로 지하 60 화정역 2번출구|2</string>
    <string>노다지복권방|031-982-7972|37.6264089|126.7051705|경기 김포시 중봉1로 81 제1층|2</string>
    <string>웅진코웨이로또판매점|031-231-8095|37.2626899|127.0297841|경기 수원시 팔달구 효원로 257 홈플러스동수원점 4층(홈플러스 동수원점)|2</string>
    <string>행운이랑대박이랑|031-255-5888|37.2988599|126.9920141|경기 수원시 장안구 만석로 99 정자부동산|2</string>
    <string>대박복권방|031-492-3512|37.3360735|126.7622824|경기 안산시 단원구 신길중앙로1길 40 101호|2</string>
    <string>복권마을|031-457-1571|37.3716109|126.9574408|경기 안양시 동안구 경수대로 547|2</string>
    <string>샘내로또판매|031-840-0225|37.8054847|127.0453732|경기 양주시 산북동 333-13|2</string>
    <string>컴닥터복권방|031-266-8119|37.3155396|127.0876048|경기 용인시 수지구 풍덕천동 239-3중앙빌딩104호|2</string>
    <string>황금복권마트|031-632-3949|37.2995267|127.438248|경기 이천시 증신로325번길 5 1층|2</string>
    <string>복권명당|-|37.0639866|127.0665305|경기 평택시 이충로 86 만민교회 1층|2</string>
    <string>천하명당|031-542-8480|37.8284495|127.1448254|경기 포천시 송우로 38|2</string>
    <string>CU(원주단관점)|033-763-4989|37.3216268|127.9560657|강원 원주시 단구로 395 1층 cu|2</string>
    <string>영화마을(현대점)|-|36.6718444|127.4866116|충북 청주시 청원구 주성로 184,(율량동)|2</string>
    <string>복권나라|043-848-2030|36.9829663|127.9285383|충북 충주시 국원대로 128|2</string>
    <string>달성로또복권판매소|041-545-6192|36.7807774|127.0079053|충남 아산시 온천대로 1531|2</string>
    <string>백합문구|041-583-3377|36.8495434|127.1198323|충남 천안시 서북구 직산읍 모시리 237-11번지 공단할인마트내|2</string>
    <string>대박복권방|063-232-2977|35.8074746|127.1312916|전북 전주시 완산구 용머리로 195|2</string>
    <string>로또명당|061-534-1313|34.5966898|126.3127296|전남 해남군 우수영로 1|2</string>
    <string>복권명당|053-857-7010|35.9139727|128.8190175|경북 경산시 금송로 1-2|2</string>
    <string>문덕대박로또|054-292-9894|35.9633131|129.4026147|경북 포항시 남구 오천읍 문덕리 문덕리 176-7|2</string>
    <string>씨유(거창대동점)|055-942-5589|35.6898904|127.9147485|경남 거창군 거창대로 93|2</string>
    <string>플러스로터리|055-366-6393|35.3310404|129.0117707|경남 양산시 범어로 28 103호 복권판매점|2</string>
    <string>코리아슈퍼|055-644-6362|34.8591131|128.4311326|경남 통영시 안개로 42 수아지오아파트 상가1층 103호|2</string>
    <string>GS25(서사라)|064-724-8680|33.5034853|126.5197222|제주 제주시 삼도1동 531-1|2</string>
</result>
