<?xml version="1.0" encoding="UTF-8"?>
<result>
    <string>GS25(구로제일)|02-830-1963|37.4919882|126.875787|서울 구로구 구로동 685-215번지103호|1</string>
    <string>스포츠베팅샵|02-3462-9011|37.4712942|127.0443274|서울 서초구 동산로 48 서희빌딩 104호|1</string>
    <string>buy the way (반포공원점)|070-7116-1666|37.509168|127.0203327|서울 서초구 반포동 709-8번지|1</string>
    <string>잠실매점|02-419-0763|37.513906|127.101373|서울 송파구 올림픽로 269 잠실역 8번출구 앞 가판|1</string>
    <string>가락하단|051-202-0449|35.1088292|128.9590703|부산 사하구 하단동 885-9번지 세븐일레븐|1</string>
    <string>각골할인마트|031-501-4420|37.2926949|126.8722903|경기 안산시 상록구 각골로 37|1</string>
    <string>OK편의점|031-635-0355|37.2798011|127.4438662|경기 이천시 중리천로 56|1</string>
    <string>CU(횡성점)|033-342-5805|37.4888103|127.9856612|강원 횡성군 횡성읍 읍하리118-1번지|1</string>
    <string>현대복권방|043-252-8345|36.6568162|127.480035|충북 청주시 청원구 향군로 140-1|1</string>
    <string>로또복권판매도통점|063-636-4883|35.4177603|127.3972431|전북 남원시 용성로 232,(도통동)|1</string>
    <string>복권나라|02-889-1355|37.4827565|126.9434903|서울 관악구 남부순환로 1739-9|2</string>
    <string>로또복권방|02-2613-0108|37.5010859|126.8448741|서울 구로구 개봉동 63-4번지|2</string>
    <string>88수퍼|02-851-8837|37.4771798|126.8921233|서울 금천구 가산로 130|2</string>
    <string>명당복권|02-969-0959|37.5778966|127.0357367|서울 동대문구 왕산로 112-1 가판|2</string>
    <string>인더라인북가좌점|02-309-3700|37.5770922|126.90927|서울 서대문구 응암로 42 1층101호|2</string>
    <string>가로판매점|02-532-6682|37.5064984|127.0048372|서울 서초구 신반포로 189 한신4차입구|2</string>
    <string>복돼지복권방|02-497-5412|37.5486111|127.0558292|서울 성동구 아차산로7길 42|2</string>
    <string>천하명당복권방|02-415-8311|37.5067897|127.1082062|서울 송파구 백제고분로41길 7 1층|2</string>
    <string>가판점(신문)|02-2636-6177|37.5344336|126.901288|서울 영등포구 양평로 48|2</string>
    <string>버스판매소|02-2679-4659|37.5187112|126.909824|서울 영등포구 영중로 2 1층(영등포동3가)|2</string>
    <string>왕대박|02-847-6637|37.5127385|126.9236066|서울 영등포구 영등포로 412|2</string>
    <string>도로가판집|02-796-0326|37.5258693|126.964413|서울 용산구 한강대로 55|2</string>
    <string>대박천하복권방|02-356-0645|37.6120797|126.9177534|서울 은평구 연서로 150 1층 1호|2</string>
    <string>신가로판매점|-|37.5586734|126.9744195|서울 중구 세종대로 26|2</string>
    <string>부일카서비스|051-637-7747|35.1400577|129.0630673|부산 동구 자성로133번길 35|2</string>
    <string>알부자로또점|051-744-4033|35.1599194|129.154692|부산 해운대구 우동 654-2번지 1층 세븐일레븐내|2</string>
    <string>훼미리마트관음점|053-326-5507|35.9382074|128.5490613|대구 북구 칠곡중앙대로 475|2</string>
    <string>로또앤토토|032-501-5633|37.4763739|126.7140248|인천 미추홀구 용정공원로 33 인천SKSkyVIEW 상가 A-2동 1층 104호|2</string>
    <string>한국종합빌딩(복권)|032-424-6093|37.4612378|126.6981723|인천 남동구 경인로 530 1층|2</string>
    <string>복권세상|062-430-9072|35.16312480000001|126.807085|광주 광산구 무진대로231번길 28 복권세상|2</string>
    <string>하나마트(하남4번로)|-|35.1907564|126.8090221|광주 광산구 하남산단4번로 172 로또카페|2</string>
    <string>선봉로또|070-8202-3428|35.5437374|129.3326805|울산 남구 삼산동 1468-6번지 CU판매점 내|2</string>
    <string>성안복권프라자|052-244-3280|35.5751597|129.3086302|울산 중구 성안동 852-2번지|2</string>
    <string>심봤다복권방|052-292-4697|35.5531661|129.3483864|울산 중구 내황13길 33-1,(반구동)|2</string>
    <string>프리웨이스토어|031-763-5369|37.4067368|127.2379576|경기 광주시 회안대로 605 1층|2</string>
    <string>CU(원종깨비점)|032-675-2997|37.5228807|126.8051686|경기 부천시 오정구 원종동 280-9번지 1F|2</string>
    <string>드림복권방|031-232-3627|37.2552427|127.0110851|경기 수원시 권선구 정조로 515|2</string>
    <string>GS25(수원우영)|031-211-2554|37.2595696|127.0442086|경기 수원시 영통구 매탄동 1263-4번지 103호|2</string>
    <string>까치복권방|031-432-7556|37.3366547|126.7482325|경기 시흥시 중심상가로 326 1층102|2</string>
    <string>GS25(원곡본)|031-491-5565|37.331666|126.793556|경기 안산시 단원구 원곡로 51|2</string>
    <string>안산예대점로또판매|031-480-7757|37.3337344|126.8125731|경기 안산시 단원구 삼일로 316 홈플러스|2</string>
    <string>훼미리복권|031-403-9965|37.3309216|126.8502785|경기 안산시 상록구 안산천동로1길 29 현대2차아파트상가18호|2</string>
    <string>인덕원복권방|031-423-8289|37.4006706|126.9762537|경기 안양시 동안구 흥안대로 523|2</string>
    <string>복권백화점|031-943-7477|37.763607|126.7699255|경기 파주시 평화로 70|2</string>
    <string>행운로또복권방|031-947-0901|37.7777694|126.8503875|경기 파주시 광탄면 신산1리215-20번지|2</string>
    <string>로또복권방|031-536-0775|37.8974113|127.2021797|경기 포천시 중앙로119번길 10|2</string>
    <string>태원통신|031-794-4318|37.5430048|127.2035104|경기 하남시 하남대로 851|2</string>
    <string>황금복권|033-743-7080|37.3412836|127.941607|강원 원주시 단계동 808번지 삼익상가 105호|2</string>
    <string>나눔로또|043-832-7930|36.8092468|127.7925916|충북 괴산군 괴산읍 동부리 667-6번지|2</string>
    <string>행운복권방|043-256-9010|36.6322322|127.4936171|충북 청주시 상당구 탑동로1번길 104,(탑동)|2</string>
    <string>로또복권|043-233-6342|36.6307251|127.5027421|충북 청주시 상당구 중고개로 344 103호|2</string>
    <string>대박찬스|043-234-4433|36.6289602|127.4364723|충북 청주시 흥덕구 가경로161번길 3,(가경동)|2</string>
    <string>대산슈퍼|041-557-3624|36.7699261|127.2502243|충남 천안시 동남구 복구정3길 1|2</string>
    <string>대박로또방|063-351-6790|35.6472076|127.5186139|전북 장수군 장천로 170|2</string>
    <string>썬|063-247-4662|35.8487595|127.1550061|전북 전주시 덕진구 우아3길 18|2</string>
    <string>대동|061-242-5224|34.8023333|126.4192996|전남 목포시 백년대로280번길 7 코사마트|2</string>
    <string>CU(포항오거리)|054-242-2229|36.0338331|129.3646721|경북 포항시 북구 죽도동 42-17번지|2</string>
    <string>삼성복권마트|055-337-9973|35.2339744|128.8520535|경남 김해시 평전로 20 우리24시슈퍼 내 좌측 복권판매점|2</string>
</result>
