<?xml version="1.0" encoding="UTF-8"?>
<result>
    <string>대박|02-3411-0863|37.4926967|127.0843455|서울 강남구 일원로3길 55|1</string>
    <string>복권명당(서부점)|053-628-6450|35.8336274|128.5548106|대구 달서구 월배로 452|1</string>
    <string>김포로또|031-982-7011|37.6193681|126.7180063|경기 김포시 돌문로 48 한솔프라자101|1</string>
    <string>버스표가판점|031-384-2165|37.3898411|126.9514106|경기 안양시 동안구 동안로 지하 130|1</string>
    <string>씨스페이스(삼성1점)|02-546-5543|37.5151537|127.0606851|서울 강남구 삼성동 106-6번지 대광빌딩1층101호|2</string>
    <string>미나식품(로또판매점)|02-2664-6793|37.573472|126.8106718|서울 강서구 금낭화로 91-12|2</string>
    <string>가로판매점|02-895-0353|37.453131|126.90073|서울 금천구 시흥대로 217 시흥동우체국|2</string>
    <string>로또복권|02-995-1500|37.6479966|127.0331608|서울 도봉구 도봉로113길 15|2</string>
    <string>럭키복권방|-|37.6530492|127.0462877|서울 도봉구 노해로63길 79 우림빌딩106|2</string>
    <string>형제상회|02-927-7260|37.5724503|127.0307388|서울 동대문구 무학로 92|2</string>
    <string>천하명당복권방|02-3472-1451|37.4797927|126.9809042|서울 동작구 동작대로7길 11|2</string>
    <string>신문가판대뚝섬역에스콰이야본사앞|02-497-9911|37.5476525|127.0447476|서울 성동구 왕십리로 114|2</string>
    <string>신문가판대|02-925-8644|37.58399259999999|127.0203641|서울 성북구 보문동4가 4번지 가판|2</string>
    <string>로또복권|02-2606-8092|37.5290788|126.8324601|서울 양천구 신월3동 205-44번지 훼미리마트|2</string>
    <string>구두로또|-|37.5380427|126.9608568|서울 용산구 효창원로 112|2</string>
    <string>훼미리마트남구청점로또판매점|051-625-3976|35.1346607|129.0917027|부산 남구 대연1동 1746-3번지 세븐일레븐내|2</string>
    <string>화랑복권|051-895-9177|35.165606|129.0393495|부산 부산진구 당감동 282-7번지 오렌지데이점포 내|2</string>
    <string>로또복권방|051-294-2011|35.104561|128.9762368|부산 사하구 낙동대로 395,(당리동)|2</string>
    <string>CU(남대구ＩＣ점)|053-521-0103|35.8376691|128.5340675|대구 달서구 본리동 659-2번지|2</string>
    <string>복권명당|053-957-7834|35.8866287|128.6423564|대구 동구 효동로 101 동촌 강나루아파트 건너편|2</string>
    <string>찬스센타백운점|032-523-4188|37.4847688|126.7087419|인천 부평구 신촌로7번길 3|2</string>
    <string>복권방|032-513-3337|37.5013699|126.7221427|인천 부평구 부평동 439-11번지|2</string>
    <string>미니스톱 평동타운점|-|35.1752285|126.8106736|광주 광산구 사암로340번길 31 부광빌딩 102호|2</string>
    <string>돼지의꿈|062-524-7199|35.1581708|126.9063217|광주 북구 경열로 212|2</string>
    <string>행운마트|062-574-6355|35.2120336|126.8731923|광주 북구 임방울대로 1059 1층 101호|2</string>
    <string>호반로또|-|35.1604899|126.8626834|광주 서구 쌍촌동 1337-2번지 호반리젠시빌아파트3차상가109호110호|2</string>
    <string>행운복권방|062-364-0645|35.1418263|126.884895|광주 서구 화운로 11-1|2</string>
    <string>금산인삼엑스포|042-634-3844|36.354311|127.4499811|대전 대덕구 비래동 140-10번지|2</string>
    <string>행운노다지복권방|042-535-8695|36.3380471|127.3843738|대전 서구 괴정동 78-1번지 다세대주택 1층|2</string>
    <string>우리들삼호점|052-221-0127|35.54997|129.2684954|울산 남구 무거동 1447-1번지|2</string>
    <string>등대복권방|-|35.4866637|129.4259058|울산 동구 동진로 4 동서아트빌 1층 편의점|2</string>
    <string>준복권방|052-289-6588|35.5526268|129.3549661|울산 북구 명촌로 91 평창리비에르2차 평창리비에르2차상가 105호|2</string>
    <string>한꿈복권방|-|35.5687712|129.3458779|울산 중구 번영로 586|2</string>
    <string>모닝마트주안점60호|052-286-4777|35.5565743|129.3414055|울산 중구 반구동 582-4번지 미니스톱편의점내|2</string>
    <string>GS25(하안연서점)|02-806-7696|37.46552430000001|126.8774687|경기 광명시 안현로 52|2</string>
    <string>약이본가|032-623-0366|37.5014656|126.7878128|경기 부천시 원미구 춘의동 202번지 테크노2차201동113호|2</string>
    <string>분당정자점로또판매점|-|37.3687428|127.1129633|경기 성남시 분당구 정자동 65-6번지|2</string>
    <string>굿타임편의점|031-714-8261|37.3496794|127.1117248|경기 성남시 분당구 구미동 25-2번지 엘레강스A109호|2</string>
    <string>노다지복권방|031-314-1016|37.448194|126.79206|경기 시흥시 복지로 103-1 1층상가|2</string>
    <string>로또명당|031-311-6362|37.4445142|126.7874847|경기 시흥시 대야동 487-19번지|2</string>
    <string>엘지25동명점|031-480-5928|37.33615899999999|126.8104867|경기 안산시 단원구 선부광장로 27 신안골드리치빌딩 122-2호|2</string>
    <string>버스표가판점|031-384-2165|37.3898411|126.9514106|경기 안양시 동안구 동안로 지하 130|2</string>
    <string>왕대박복권방|031-375-3005|37.1276531|127.0766707|경기 오산시 오산로 13,(갈곶동)|2</string>
    <string>K-마트|031-877-8308|37.7236002|127.0477478|경기 의정부시 평화로 359 회룡한주아파트 상가동 110호|2</string>
    <string>천하명당|031-631-5080|37.3071519|127.4021953|경기 이천시 경충대로 3145 목도빌딩|2</string>
    <string>진성복권방|031-541-0987|37.8475251|127.1911618|경기 포천시 가산로 380|2</string>
    <string>대박찬스복권전문점|031-543-9038|37.8257572|127.1440613|경기 포천시 소흘읍 송우리 452-9번지|2</string>
    <string>로뎀|031-232-4215|37.2116472|126.8555023|경기 화성시 주석로 237|2</string>
    <string>GS25(청주수곡점)|043-286-9777|36.6160336|127.4729697|충북 청주시 서원구 수곡동 910|2</string>
    <string>맨투맨복권방|043-274-5027|36.66747|127.451927|충북 청주시 흥덕구 송화로166번길 14 편의점|2</string>
    <string>공주복권방|041-854-3744|36.4591245|127.1251284|충남 공주시 웅진로 210-2|2</string>
    <string>777천하명당|041-953-9900|36.0748413|126.6889892|충남 서천군 충절로 54|2</string>
    <string>제이민온천복권|041-548-2322|36.78635360000001|127.0146005|충남 아산시 번영로217번길 25 웨이스탑 편의점|2</string>
    <string>플러스복권방|063-835-0990|35.9609214|126.9785181|전북 익산시 하나로13길 18|2</string>
    <string>구례로또|061-783-0645|35.2087017|127.4648189|전남 구례군 구례읍 로터리길 2-1|2</string>
    <string>금산로또|055-761-5738|35.2139334|128.1403232|경남 진주시 금산면 중천리 331-7번지|2</string>
    <string>창원병원앞매표소|055-266-2460|35.2187449|128.6724378|경남 창원시 성산구 중앙동 104-1번지 가판|2</string>
    <string>돌하르방복권|064-762-5735|33.2469912|126.560047|제주 서귀포시 태평로353번길 9|2</string>
    <string>행운복권방|064-796-8228|33.41369220000001|126.2644611|제주 제주시 한림중앙로 12|2</string>
    <string>한라점|064-747-3651|33.48212230000001|126.4737599|제주 제주시 노형동 2519-14 씨유대화점내|2</string>
</result>
