<?xml version="1.0" encoding="UTF-8"?>
<result>
    <string>복권전문점|02-981-9864|37.615535|127.0286461|서울 강북구 솔샘로64길 43,(미아동)|1</string>
    <string>장안홈타운|02-2244-3661|37.5679378|127.0738227|서울 동대문구 장한로18길 88|1</string>
    <string>굿-7|051-752-4743|35.1552737|129.1176812|부산 수영구 광안로 49|1</string>
    <string>동광슈퍼|062-363-9428|35.1548829|126.9015815|광주 서구 천변좌로 228|1</string>
    <string>대박찬스|031-528-5530|37.7197407|127.1839325|경기 남양주시 진접읍 장현로 111 1층1호|1</string>
    <string>대운복권|031-754-6426|37.4322274|127.1286677|경기 성남시 중원구 성남대로 1149|1</string>
    <string>행복충전소|031-664-1210|37.0817613|127.0564036|경기 평택시 탄현로 332-2|1</string>
    <string>중앙로또(로손편의점내)|054-975-1666|36.0714646|128.3428215|경북 칠곡군 북삼로 41 복권판매점|1</string>
    <string>로또복권|055-542-4010|35.1534429|128.707114|경남 창원시 진해구 냉천로 93 그린프라자 이마트24편의점|1</string>
    <string>강동로또|070-4101-0888|37.5499949|127.1724122|서울 강동구 상일동 249번지|2</string>
    <string>강동로또|070-4101-0888|37.5499949|127.1724122|서울 강동구 상일동 249번지|2</string>
    <string>해와달|02-719-7879|37.5471992|126.9340928|서울 마포구 독막로 184-1|2</string>
    <string>강원슈퍼|02-303-2549|37.5816075|126.9355486|서울 서대문구 모래내로 355|2</string>
    <string>영광정보통신|02-911-5016|37.6026597|127.0424818|서울 성북구 화랑로 92 1층 우측1호|2</string>
    <string>행복슈퍼|02-741-5788|37.5909824|127.0111289|서울 성북구 동소문로 49|2</string>
    <string>혜성슈퍼|02-406-5020|37.4934133|127.1260213|서울 송파구 송이로27길 9|2</string>
    <string>천하명당복권방|02-717-6475|37.5338448|126.9627141|서울 용산구 신계동 36-11번지|2</string>
    <string>명동역5번출구가판|02-319-8753|37.5610141|126.9845097|서울 중구 퇴계로 115|2</string>
    <string>명지복권방|051-271-7515|35.0828367|128.904213|부산 강서구 명지오션시티5로 16 103호|2</string>
    <string>하나열쇠|051-627-4088|35.1162954|129.1112894|부산 남구 용호로 179|2</string>
    <string>태향슈퍼|051-751-4166|35.1691985|129.1128617|부산 수영구 수영동 451-13번지|2</string>
    <string>복권토큰판매소|053-653-8455|35.8409712|128.5820851|대구 남구 대명로 230 토큰박스|2</string>
    <string>복권명당(서부점)|053-628-6450|35.8336274|128.5548106|대구 달서구 월배로 452|2</string>
    <string>왕대박로또|053-581-9361|35.8413021|128.5491189|대구 달서구 구마로39길 88 1층 9,10,11호|2</string>
    <string>세진전자통신|053-566-4466|35.871901|128.5552024|대구 서구 서대구로 156,(평리동)|2</string>
    <string>복권천하|032-542-0232|37.5469165|126.7374664|인천 계양구 임학동로 58|2</string>
    <string>구월퍼스트점|032-461-7322|37.4526431|126.7106869|인천 남동구 구월동 1200-2번지 cu 편의점내|2</string>
    <string>마이마트|032-561-3433|37.5431051|126.678259|인천 서구 탁옥로 76 한국상가제1층101호|2</string>
    <string>마이마트|032-561-3433|37.5431051|126.678259|인천 서구 탁옥로 76 한국상가제1층101호|2</string>
    <string>복권방|032-822-8249|37.4246728|126.6830182|인천 연수구 비류대로433번길 10 103호|2</string>
    <string>천하복권방|032-764-1600|37.4707718|126.6243974|인천 중구 신포로 19,(중앙동4가)|2</string>
    <string>형제기획 복권시대|062-228-4872|35.1512609|126.9141558|광주 동구 금남로 193-1 복권시대|2</string>
    <string>SM정보통신|062-513-3490|35.1878976|126.8681773|광주 북구 동림용산로 18|2</string>
    <string>배팅샵(가장)|042-523-4797|36.32915|127.3866569|대전 서구 갈마로 318 1층 복권방|2</string>
    <string>GS25(대전태평점)|042-527-2534|36.3225485|127.3987458|대전 중구 유천동 189-5번지 백강미소빌딩|2</string>
    <string>우리들편의점(행운점)|052-227-7110|35.5382599|129.3220569|울산 남구 삼산로143번길 23 이마트24울산동평점|2</string>
    <string>우리들현대점|052-258-7779|35.5065071|129.3093011|울산 남구 선암동 587-19번지 거북이편의점 내|2</string>
    <string>영화유통(1등복권방)|052-269-9851|35.5338415|129.3221564|울산 남구 신정로 19 삼성아파트 상가 204-101|2</string>
    <string>씨엔마트|-|35.548169|129.3240161|울산 남구 삼신로6번길 9|2</string>
    <string>우리들복산점|-|35.5620331|129.3359946|울산 중구 복산동(복산2동) 32-29 우리들편의점|2</string>
    <string>코사마트한양점|031-962-0122|37.658411|126.8395542|경기 고양시 덕양구 마상로 156|2</string>
    <string>프리웨이스토어|031-763-5369|37.4067368|127.2379576|경기 광주시 회안대로 605 1층|2</string>
    <string>프리웨이스토어|031-763-5369|37.4067368|127.2379576|경기 광주시 회안대로 605 1층|2</string>
    <string>홈돌이로또복권|031-999-8082|37.6240028|126.6987451|경기 김포시 중봉로 14 삼성홈플러스2층|2</string>
    <string>버스매표소|032-656-9688|37.4869824|126.7836891|경기 부천시 부천로 32 도로부지|2</string>
    <string>복권왕국|032-668-8494|37.50167760000001|126.7562841|경기 부천시 조마루로105번길 34-7|2</string>
    <string>미래복권닷컴|031-707-5003|37.3712098|127.1405241|경기 성남시 분당구 장안로25번길 28 건영아파트상가114호|2</string>
    <string>드림|031-223-7532|37.2637879|127.0142519|경기 수원시 권선구 정조로 615|2</string>
    <string>25시슈퍼|031-431-6273|37.3624111|126.72997|경기 시흥시 함송로14번길 13-17 홍익프라자1층107호|2</string>
    <string>중앙로또|031-413-7786|37.3150628|126.8252415|경기 안산시 단원구 고잔동(호수동) 681-7 대덕프라자102호|2</string>
    <string>건강기능식품판매점|031-437-9371|37.2975601|126.8651559|경기 안산시 상록구 본오로 133 우성아파트 상가동 우성아파트상가 114호|2</string>
    <string>샘내로또판매|031-840-0225|37.8054847|127.0453732|경기 양주시 산북동 333-13번지|2</string>
    <string>행운|031-275-4014|37.2938207|127.1206578|경기 용인시 기흥구 언남동 336-7번지 멀티프라자104호|2</string>
    <string>월롱엘지복권방|031-942-9753|37.8118821|126.7562226|경기 파주시 월롱면 덕은리 1247 105호 (파크뷰)|2</string>
    <string>로또복권|031-357-9003|37.2111441|126.7332036|경기 화성시 사강로 172|2</string>
    <string>왕대박복권|033-638-0292|38.2113469|128.5893241|강원 속초시 번영로 142 1층, 102호|2</string>
    <string>인제복권방|033-463-0645|38.0681406|128.1727601|강원 인제군 인제읍 비봉로 11-1,(상동리)|2</string>
    <string>행운로또|033-253-0395|37.878316|127.7299982|강원 춘천시 금강로 81 신한은행강원영업부지점앞 가판|2</string>
    <string>407억당첨가판점|033-256-4710|37.8791912|127.7266262|강원 춘천시 중앙로 65 국민은행앞 가판|2</string>
    <string>희망로또|041-853-9382|36.4677879|127.1350262|충남 공주시 신관로 77 1층 상가|2</string>
    <string>GS25(천안역점)|041-551-1025|36.8090743|127.148308|충남 천안시 동남구 대흥동 96-1번지|2</string>
    <string>종합복권방|061-536-8161|34.5707411|126.6109401|전남 해남군 해남로 34 종합복권방편의점|2</string>
    <string>울릉로또|054-791-6355|37.4980575|130.9081339|경북 울릉군 봉래2길 32-14 1층 울릉로또&amp;커피|2</string>
    <string>나눔로또 칠곡(부산방향)휴게소|054-975-1544|35.9800294|128.3982179|경북 칠곡군 칠곡대로 1485 아이나비 매장내 복권판매점|2</string>
    <string>중앙로또(로손편의점내)|054-975-1666|36.0714646|128.3428215|경북 칠곡군 북삼로 41 복권판매점|2</string>
    <string>천하명당 복권당|055-521-3683|35.4567197|128.5268496|경남 창녕군 연지길 3 1층 CU편의점 내|2</string>
    <string>제주대림점|064-746-5525|33.4787091|126.4876659|제주 제주시 과원북2길 48|2</string>
</result>
