<?xml version="1.0" encoding="UTF-8"?>
<result>
    <string>경성식품|02-2243-2680|37.5905196|127.060212|서울 동대문구 망우로21길 52|1</string>
    <string>주아킹 목동점|-|37.5275081|126.8637975|서울 양천구 목동로 213 1층|1</string>
    <string>복권명당(서부점)|053-628-6450|35.8336208|128.5548528|대구 달서구 월배로 452|1</string>
    <string>천하명당복권|053-311-0645|35.9443045|128.5506277|대구 북구 칠곡중앙대로 545|1</string>
    <string>평화(북구사수점)|053-321-0941|35.8965441|128.5195654|대구 북구 한강로 92 1층 101호|1</string>
    <string>버스표판매소|031-978-1143|37.6190435|126.8404776|경기 고양시 덕양구 화신로 76 샘터마을1단지아파트 971번지선|1</string>
    <string>인생로또 645|031-554-0645|37.625124|127.155339|경기 남양주시 다산순환로 356 다산푸리마타워 1층 102호|1</string>
    <string>노다지복권방|032-657-9290|37.4680292|126.8240057|경기 부천시 양지로 205 1층 118호|1</string>
    <string>왕대박유통|043-276-9195|36.6245093|127.429256|충북 청주시 흥덕구 서현동로 25 화인프라자 1층|1</string>
    <string>채널큐|055-222-6695|35.2175322|128.5814317|경남 창원시 마산합포구 산호남로 11-1|1</string>
    <string>행운&amp;빈센트|-|33.2490113|126.5669824|제주 서귀포시 동문로 64|1</string>
    <string>역삼대박황제복권방|-|37.5067902|127.0369388|서울 강남구 논현로106길 31 나무빌딩 101호 cu편의점|2</string>
    <string>골드(복권판매점)|02-989-6000|37.6337406|127.0236897|서울 강북구 도봉로 284 1층 1호|2</string>
    <string>금강식품|02-2608-9462|37.5443834|126.8373906|서울 강서구 강서로 207 영신빌딩|2</string>
    <string>로또카페|-|37.5678613|126.8415595|서울 강서구 강서로74길 3 1층 6호|2</string>
    <string>가판대|02-3491-7610|37.6857362|127.0480605|서울 도봉구 마들로 859-19 도봉산역 1번출구앞 가판대|2</string>
    <string>복권나라|02-814-6824|37.504378|126.9387461|서울 동작구 상도로 178 최안과 1층 101호|2</string>
    <string>복권나라|02-814-6824|37.504378|126.9387461|서울 동작구 상도로 178 최안과 1층 101호|2</string>
    <string>복권천국방|02-337-3259|37.5542187|126.9123925|서울 마포구 동교로 92 1층|2</string>
    <string>금손복권|-|37.5418659|126.9523007|서울 마포구 새창로 22 1층(도화동)|2</string>
    <string>럭키슈퍼|02-753-0330|37.55059869999999|126.9773818|서울 용산구 후암로 52|2</string>
    <string>월드24시|02-385-5664|37.6192218|126.9198046|서울 은평구 통일로 855-15|2</string>
    <string>노다지복권방|02-2233-6331|37.5650533|127.0177829|서울 중구 다산로44길 15|2</string>
    <string>범일서적|051-632-2672|35.1373681|129.0589586|부산 동구 진시장로 19-2 1층복권방|2</string>
    <string>복권판매점|-|35.1299464|129.04778|부산 동구 고관로 130-2 1층|2</string>
    <string>복권판매점 천하제일명당|-|35.1436218|129.060141|부산 부산진구 골드테마길 42|2</string>
    <string>행운나눔로또|051-256-2510|35.0982959|129.0322987|부산 중구 구덕로34번길 4 가판집|2</string>
    <string>복권명당(서부점)|053-628-6450|35.8336208|128.5548528|대구 달서구 월배로 452|2</string>
    <string>황금로또|053-637-0027|35.6574069|128.4180795|대구 달성군 과학마을로3길 14 반도유보라 상가 황금 부동산 내|2</string>
    <string>행복나라|-|35.8896436|128.5828783|대구 북구 침산남로 63 1층2번째상가|2</string>
    <string>복권나라|053-521-2864|35.8609189|128.5383508|대구 서구 와룡로 318,(중리동)|2</string>
    <string>지원복권방|-|35.867207|128.5706237|대구 서구 달서로 55 1층 주차장내 상가|2</string>
    <string>복권천국|032-519-8133|37.51770920000001|126.7340042|인천 부평구 평천로391번길 4 102호|2</string>
    <string>로또100|-|37.5320814|126.6449762|인천 서구 청라커낼로 264 1층 101-A호(청라동, 청라두손중앙프라자)|2</string>
    <string>드림|062-941-1357|35.1465196|126.7774325|광주 광산구 선운로20번길 64 104호|2</string>
    <string>행운플러스|042-931-5920|36.4394696|127.4238854|대전 대덕구 덕암로 214|2</string>
    <string>열매로또복권|-|36.375057|127.32048|대전 유성구 은구비서로 31-1 102호, 지족동|2</string>
    <string>이마트24울산삼산본동점|052-256-1225|35.5427263|129.3535257|울산 남구 돋질로 445|2</string>
    <string>황제복권|-|35.5310832|129.3126747|울산 남구 수암로 42|2</string>
    <string>이마트24백석동문점|031-903-7863|37.6394317|126.7870398|경기 고양시 일산동구 호수로 358-26 203동1층 101호|2</string>
    <string>싱글벙글마트|02-2616-8176|37.47781459999999|126.8539099|경기 광명시 광명로 884 1층 좌측호(광명동)|2</string>
    <string>웃자로또|070-4128-8368|37.3610003|127.2268726|경기 광주시 오포로 775|2</string>
    <string>대박로또복권|-|37.3621099|126.9422636|경기 군포시 당산로135번길 47 102호(금정동)|2</string>
    <string>대명로또편의점|031-863-3172|37.9049536|127.0535368|경기 동두천시 중앙로 263|2</string>
    <string>복권천국|032-673-8722|37.5284682|126.8145004|경기 부천시 고강로92번길 41|2</string>
    <string>로또대박|-|37.5031919|126.7619547|경기 부천시 석천로177번길 11 제이클래스중동 1층 105호|2</string>
    <string>복권왕국|032-653-7824|37.4829851|126.779553|경기 부천시 경인로216번길 7 1층|2</string>
    <string>디딤슈퍼|032-675-6098|37.5106364|126.7805575|경기 부천시 도약로 279|2</string>
    <string>현대사|031-716-2300|37.3456079|127.111102|경기 성남시 분당구 미금일로 77 102호|2</string>
    <string>미금헤리츠점|070-8815-1822|37.3492879|127.1083139|경기 성남시 분당구 성남대로 151 엠코헤리츠 1층110호|2</string>
    <string>권선로또복권방|070-4502-3842|37.2708511|126.9750291|경기 수원시 권선구 탑동로 22 천림빌딩 천림빌딩102호|2</string>
    <string>호수공원 복권방|-|37.2825174|127.0574661|경기 수원시 영통구 광교호수공원로 277 광교중흥에스클래스 제지1층 제비1-053호|2</string>
    <string>천하명당우만점|031-257-7769|37.2902606|127.030149|경기 수원시 팔달구 월드컵로369번길 4|2</string>
    <string>천하명당우만점|031-257-7769|37.2902606|127.030149|경기 수원시 팔달구 월드컵로369번길 4|2</string>
    <string>옹이로또복권|-|37.2775792|127.0019798|경기 수원시 팔달구 팔달로99번길 22 (화서동)|2</string>
    <string>로또대박복권|-|37.0084007|127.2695912|경기 안성시 백성1길 5|2</string>
    <string>산타복권방|-|37.0078137|127.2583489|경기 안성시 아양1로 77-10 해천프라자 제1동 104호|2</string>
    <string>로또복권방|031-879-1220|37.7117549|127.0473018|경기 의정부시 평화로 223,(호원동)|2</string>
    <string>소망로또|-|37.7074263|127.0484393|경기 의정부시 평화로 176|2</string>
    <string>행운복권방|031-851-1764|37.7367482|127.0871477|경기 의정부시 충의로 55|2</string>
    <string>당첨희망복권점|031-633-0647|37.2819112|127.4383495|경기 이천시 영창로 145 관고사거리|2</string>
    <string>신가네|-|37.795083|126.7910424|경기 파주시 다락고개길 113 1층 일부|2</string>
    <string>서정천하명당|031-611-4097|37.0581065|127.0593319|경기 평택시 송탄로 160|2</string>
    <string>우리 복권판매점|-|37.8382399|127.1651252|경기 포천시 가산로 109|2</string>
    <string>유니콘|-|37.541072|127.1994957|경기 하남시 신우실로63번길 11 A 101호|2</string>
    <string>샤방샤방|031-355-2211|37.134387|126.8960453|경기 화성시 서해로 808|2</string>
    <string>화성메타복권|-|37.2135593|127.0417698|경기 화성시 병점1로 221 101호|2</string>
    <string>로또부자세상|033-731-7793|37.3545157|127.9545973|강원 원주시 천사로 286 1층|2</string>
    <string>복권나라|033-735-3824|37.3559874|127.9439385|강원 원주시 원일로 219 1층|2</string>
    <string>21세기로또|-|37.148179|128.2147668|충북 제천시 의림대로 234-2 1층|2</string>
    <string>복터져|-|36.6732867|127.4900571|충북 청주시 청원구 율량로 36 103호|2</string>
    <string>행복복권방|-|36.6160139|127.4410462|충북 청주시 흥덕구 풍년로 26 명인투플러스|2</string>
    <string>행운을주는사람들|043-847-3377|36.9876485|127.931629|충북 충주시 연수상가길 42 1층 복권방|2</string>
    <string>도깨비|-|36.9848226|127.9260904|충북 충주시 금릉로 91 1층 복권방|2</string>
    <string>서산로또명당점|-|36.7712975|126.4366917|충남 서산시 서해로 3207 세븐일레븐편의점 옆|2</string>
    <string>노다지복권방|-|36.808604|127.1619163|충남 천안시 동남구 원성천1길 151 2호|2</string>
    <string>천안역로또토토복권방|041-555-9280|36.809094|127.1477791|충남 천안시 동남구 대흥로 237 아시아마트내|2</string>
    <string>운수대통복권방|041-554-1259|36.8004997|127.1492726|충남 천안시 동남구 대흥로 122 중앙시장 입구|2</string>
    <string>잉크와복권방|041-592-1677|36.8021368|127.1394482|충남 천안시 동남구 차돌로 84|2</string>
    <string>천안역로또토토복권방|041-555-9280|36.809094|127.1477791|충남 천안시 동남구 대흥로 237 아시아마트내|2</string>
    <string>플러스24쌍용본점|041-578-1066|36.797218|127.11814|충남 천안시 서북구 월봉로 74|2</string>
    <string>대박복권방|063-232-2977|35.8075105|127.1312744|전북 전주시 완산구 용머리로 195|2</string>
    <string>삼천리로또|061-362-1144|35.2798491|127.2966492|전남 곡성군 곡성읍 곡성로 853 편의점 내|2</string>
    <string>제일마트|061-337-1371|35.0311418|126.719728|전남 나주시 중앙로 21 제일마트|2</string>
    <string>현아비디오로또|061-741-8224|0|0|전남 순천시 풍덕주택길 90 현아복권방|2</string>
    <string>추섬로또|-|34.3227171|126.7426287|전남 완도군 개포로145번길 44-4 제2호|2</string>
    <string>진도효자로또|-|34.4812928|126.2692886|전남 진도군 동외1길 8 1층|2</string>
    <string>광장로또판매점|-|36.1307348|128.3319886|경북 구미시 산업로4길 52 1층|2</string>
    <string>대박복권방|054-834-3999|36.3489881|128.6972808|경북 의성군 중앙길 52|2</string>
    <string>행운복권방|-|35.96546|129.4032771|경북 포항시 남구 원동로 28|2</string>
    <string>행복충전|-|36.0974099|129.3710637|경북 포항시 북구 삼흥로 441 3호|2</string>
    <string>우주로또|054-261-8863|36.1120196|129.3477008|경북 포항시 북구 흥해로81번길 2-1 위드유커피숍내|2</string>
    <string>삼방동토토플러스복권방|055-335-3981|35.2493695|128.9102929|경남 김해시 삼안로 239|2</string>
    <string>로또판매업|055-366-7119|35.3590045|129.0436994|경남 양산시 북정로 31 CU편의점 내|2</string>
    <string>해밀통신|-|35.1197752|128.487828|경남 창원시 마산합포구 진북산업로 41 1층|2</string>
    <string>대박찬스|055-224-5282|35.2029094|128.5661873|경남 창원시 마산합포구 자산삼거리로 16|2</string>
    <string>만복슈퍼|055-298-2988|35.31928449999999|128.6028993|경남 창원시 의창구 천주로 732|2</string>
    <string>달인촌|-|33.2501737|126.5634281|제주 서귀포시 중앙로62번길 18|2</string>
    <string>씨유제주 제일점|-|33.5119228|126.5314344|제주 제주시 신산로 16 CU 제일점|2</string>
</result>
