<?xml version="1.0" encoding="UTF-8"?>
<result>
    <string>스파|02-951-6465|37.661671|127.05789|서울 노원구 동일로 1493 주공10단지종합상가111|1</string>
    <string>서재강변로또|053-591-3747|35.878706|128.497475|대구 달성군 서재로 172|1</string>
    <string>황금복권방|032-813-0642|37.394943|126.65016|인천 연수구 컨벤시아대로 81 송도동 드림시티 113-2호|1</string>
    <string>우리복권|032-422-5008|37.401684|126.72308|인천 남동구 논고개로123번길 17 109호|1</string>
    <string>또로또|052-257-6980|35.539259|129.3261|울산 남구 신정로68번길 47 1층 신화부동산|1</string>
    <string>봉담복자리복권과편의점|031-227-0071|37.219655|126.948774|경기 화성시 삼천병마로 1276|1</string>
    <string>황금복권마트|031-632-3949|37.299417|127.43798|경기 이천시 증신로325번길 5 1층|1</string>
    <string>도원로또방|-|37.43513|126.800983|경기 시흥시 은계중앙로 65 상가동 제1층 제1호|1</string>
    <string>한아름 복권|-|37.60372|126.77057|경기 김포시 장차로 19 102호|1</string>
    <string>바다 복권판매점|-|36.649758|127.485124|충북 청주시 청원구 직지대로 855|1</string>
    <string>세븐복권|-|36.776863|127.569044|충북 증평군 초중6길 19 1층(세븐일레븐 내)|1</string>
    <string>로또 계룡에스파|-|36.265475|127.25871|충남 계룡시 대실남북3길 16 계룡 한라비발디센트럴 상가 5호|1</string>
    <string>로또복권보성점|054-247-8239|36.039135|129.3482|경북 포항시 북구 용흥로 126 보성아파트상가101호|1</string>
    <string>로또명당|-|36.345303|128.69848|경북 의성군 중앙길 10-1 1층|1</string>
    <string>노다지로또|02-434-3020|37.589488|127.091767|서울 중랑구 겸재로 217|2</string>
    <string>가판14호|02-778-8638|37.557811|126.9768|서울 중구 퇴계로 37|2</string>
    <string>제이복권방|02-764-3232|37.571252|127.00283|서울 종로구 종로 225-1 평창빌딩 1층 103호|2</string>
    <string>우선식품|02-833-0049|37.512497|126.91667|서울 영등포구 도신로 231-2|2</string>
    <string>교통카드판매대|02-786-2480|37.523777|126.92687|서울 영등포구 여의나루로 71|2</string>
    <string>로그인편의점|-|37.560824|127.06655|서울 성동구 천호대로 430 103호 로그인편의점|2</string>
    <string>인터넷 복권판매사이트|02-1588-6450|37.482063|127.015788|동행복권(dhlottery.co.kr)|2</string>
    <string>축복 복권|-|37.569458|126.914|서울 서대문구 수색로 39 1층|2</string>
    <string>복권백화점|02-3142-6478|37.561607|126.90478|서울 마포구 월드컵로 157|2</string>
    <string>미래복권|02-978-2011|37.62519|127.07262|서울 노원구 동일로191길 7 1층|2</string>
    <string>아차산역가로판매점|02-456-6324|37.551611|127.09016|서울 광진구 천호대로 665|2</string>
    <string>또와식품|02-3665-4377|37.550114|126.87285|서울 강서구 양천로 694|2</string>
    <string>행운복권|-|37.619958|127.01623|서울 강북구 솔샘로 212 1층|2</string>
    <string>로또은행복권방|-|37.632043|127.02413|서울 강북구 도봉로 264 1층 101호|2</string>
    <string>대박복권방|-|37.547798|127.14435|서울 강동구 양재대로134길 11 1층 4호|2</string>
    <string>부일카서비스|051-637-7747|35.140055|129.06305|부산 동구 자성로133번길 35|2</string>
    <string>부일카서비스|051-637-7747|35.140055|129.06305|부산 동구 자성로133번길 35|2</string>
    <string>돈벼락맞는곳|051-636-3669|35.139161|129.05993|부산 동구 조방로49번길 18-1|2</string>
    <string>돈벼락맞는곳|051-723-0244|35.245199|129.21633|부산 기장군 읍내로 109|2</string>
    <string>씨스페이스 범어사역점|-|35.271634|129.09242|부산 금정구 중앙대로 2097|2</string>
    <string>월드복권|-|35.878425|128.54368|대구 서구 북비산로 98|2</string>
    <string>드림복권방|032-882-1800|37.464673|126.63202|인천 중구 인중로 97-1 버스정류장 앞 GS편의점 옆|2</string>
    <string>희망복권|-|37.497647|126.67073|인천 서구 가정로151번길 11 삼성홈플러스가좌점1층|2</string>
    <string>연이네 복권방|-|37.59548|126.67131|인천 서구 완정로 26 수옥빌딩 1층|2</string>
    <string>하영|032-568-2747|37.530947|126.65632|인천 서구 청라에메랄드로 65 아파트 상가 102호|2</string>
    <string>행운복권|032-863-9619|37.469091|126.67959|인천 미추홀구 길파로35번길 2 종합전기전자 맞은편|2</string>
    <string>인생한방|-|35.118124|126.931049|광주 동구 화산로 328-6 상가 106호 GS25 용산호반점|2</string>
    <string>동탄호수복권|-|37.166089|127.10728|경기 화성시 동탄순환대로 127-5 1층 101호|2</string>
    <string>어쩌면 오늘|-|37.204631|127.052606|경기 화성시 여울로2길 32 1층|2</string>
    <string>행운복권|031-795-5536|37.550685|127.18447|경기 하남시 조정대로 45 R110호|2</string>
    <string>잘찍어로또방|031-683-0708|36.988481|126.92799|경기 평택시 안현로서5길 64|2</string>
    <string>로또대박|-|37.828973|126.83897|경기 파주시 술이홀로 470|2</string>
    <string>이마트24삼융시네마점|-|37.713157|126.75989|경기 파주시 경의로 1074|2</string>
    <string>자매점|031-954-1442|37.762697|126.77473|경기 파주시 문화로 95 1층|2</string>
    <string>칠성복권방|-|37.235736|127.20738|경기 용인시 처인구 금령로 99-1 1층 101호|2</string>
    <string>칠성복권방|-|37.235736|127.20738|경기 용인시 처인구 금령로 99-1 1층 101호|2</string>
    <string>칠성복권방|-|37.235736|127.20738|경기 용인시 처인구 금령로 99-1 1층 101호|2</string>
    <string>칠성복권방|-|37.235736|127.20738|경기 용인시 처인구 금령로 99-1 1층 101호|2</string>
    <string>칠성복권방|-|37.235736|127.20738|경기 용인시 처인구 금령로 99-1 1층 101호|2</string>
    <string>칠성복권방|-|37.235736|127.20738|경기 용인시 처인구 금령로 99-1 1층 101호|2</string>
    <string>칠성복권방|-|37.235736|127.20738|경기 용인시 처인구 금령로 99-1 1층 101호|2</string>
    <string>칠성복권방|-|37.235736|127.20738|경기 용인시 처인구 금령로 99-1 1층 101호|2</string>
    <string>칠성복권방|-|37.235736|127.20738|경기 용인시 처인구 금령로 99-1 1층 101호|2</string>
    <string>칠성복권방|-|37.235736|127.20738|경기 용인시 처인구 금령로 99-1 1층 101호|2</string>
    <string>하늘로또|-|37.257895|127.64641|경기 여주시 세종로475번길 2 1층|2</string>
    <string>신세계로또|031-772-4798|37.492202|127.49919|경기 양평군 공흥로 16 1층|2</string>
    <string>대박나라|-|37.301135|126.81331|경기 안산시 단원구 원포공원1로 30 1층 122호|2</string>
    <string>로또명당카페|-|37.326875|126.67705|경기 시흥시 거북섬2길 21 1층 103호|2</string>
    <string>희망복권|-|37.392128|126.74172|경기 시흥시 월곶중앙로14번길 68 1동 104호|2</string>
    <string>럭키복권방|-|37.288151|127.0574|경기 수원시 영통구 센트럴타운로 15 아이플렉스104호|2</string>
    <string>금곡로|-|37.275054|126.95274|경기 수원시 권선구 금곡로197번길 18-23 105호(금곡동 해피라움블루)|2</string>
    <string>태인(금돼지) 복권|-|37.35035|127.11133|경기 성남시 분당구 돌마로 85 제105호(금곡동 동양프라자)|2</string>
    <string>로또복권로데오서현점|-|37.38407|127.12263|경기 성남시 분당구 분당로53번길 20 1층 109호(서현동 이랜드분당프라자)|2</string>
    <string>풍전슈퍼|032-664-8909|37.497089|126.79116|경기 부천시 조마루로 428|2</string>
    <string>행운드림복권|-|37.500273|126.75615|경기 부천시 조마루로105번길 8-12 103호|2</string>
    <string>씨유 학운중앙점|-|37.610159|126.60092|경기 김포시 황금4로 99 101호|2</string>
    <string>행운복권방(매산리)|-|37.369978|127.24637|경기 광주시 양벌로 329|2</string>
    <string>행복한사람들 (흥부네)|031-763-7781|37.369896|127.3039|경기 광주시 경충대로 1014|2</string>
    <string>대박복권방|-|37.691027|126.75917|경기 고양시 일산서구 경의로 823 1층|2</string>
    <string>교통카드충전소|031-978-0261|37.63452|126.83222|경기 고양시 덕양구 화정로 58 화정역 2번출구|2</string>
    <string>일등유통|033-633-8157|38.213934|128.59641|강원 속초시 중앙로 274 1층|2</string>
    <string>복권명가|-|37.497387|129.12488|강원 동해시 송정로 47-1 102호|2</string>
    <string>도깨비|043-265-7727|36.656214|127.46928|충북 청주시 흥덕구 사운로 330|2</string>
    <string>행운복권방|043-255-0210|36.618726|127.498006|충북 청주시 상당구 단재로 119|2</string>
    <string>사거리로또|-|36.929767|127.68185|충북 음성군 음성로 91 1층|2</string>
    <string>수레크레이션이벤트기획|041-554-3118|36.827862|127.1335|충남 천안시 서북구 성정중4길 3 증축 1층동 4호(동물병원 옆 복권방)|2</string>
    <string>유구복권방|041-841-4777|36.550635|126.95251|충남 공주시 중앙2길 70 1층|2</string>
    <string>터미널복권방|063-532-5382|35.572332|126.84496|전북 정읍시 연지8길 6|2</string>
    <string>세븐일레븐 전주상산타운점|-|35.804023|127.116557|전북 전주시 완산구 거마평로 127|2</string>
    <string>썬|063-247-4662|35.848779|127.15499|전북 전주시 덕진구 우아3길 18|2</string>
    <string>왕대박로또|-|35.849774|127.077346|전북 전주시 덕진구 만성북로 19 조은 프라자 106호|2</string>
    <string>행운복권방 보생당건강원|063-831-6040|35.960347|126.99724|전북 익산시 무왕로 1268|2</string>
    <string>알리바이금당점|061-721-1281|34.945647|127.52628|전남 순천시 대석길 44|2</string>
    <string>복권나라|054-255-3074|36.08079|129.39602|경북 포항시 북구 장량로140번길 9|2</string>
    <string>복권판매점 약목점|-|36.033006|128.36592|경북 칠곡군 약목로 75-3 1층|2</string>
    <string>덕성로또|-|37.482649|130.90831|경북 울릉군 도동길 52|2</string>
    <string>덕성로또|-|37.482649|130.90831|경북 울릉군 도동길 52|2</string>
    <string>덕성로또|-|37.482649|130.90831|경북 울릉군 도동길 52|2</string>
    <string>복권일번지|054-536-7838|36.415815|128.166478|경북 상주시 중앙로 256|2</string>
    <string>왕대박(원평점)|070-8613-8990|36.146241|128.348|경북 구미시 선산대로 183|2</string>
    <string>미니풀 복권판매점|054-465-6556|36.089808|128.35496|경북 구미시 상사서로 81|2</string>
    <string>CU노서점|054-745-3140|35.841009|129.20302|경북 경주시 금성로259번길 38 1층 CU 노서점 내|2</string>
    <string>행복나눔복권방|-|35.219476|128.70218|경남 창원시 성산구 창이대로 733 상가A동 2층 204호|2</string>
    <string>구산복권방|-|35.250892|128.872208|경남 김해시 가락로 291 107호|2</string>
    <string>화북1등복권방|064-755-1388|33.520699|126.56562|제주 제주시 진남로6길 21|2</string>
</result>
