<?xml version="1.0" encoding="UTF-8"?>
<result>
    <string>아현역3번출구앞가판점|02-392-9580|37.557008|126.9579724|서울 마포구 마포대로 249 아현산업정보학교 아현역3번출구앞|1</string>
    <string>로또명당|032-435-2412|37.4384349|126.6810538|인천 미추홀구 문학길 4 편의점내|1</string>
    <string>꽃돼지복권|042-625-3935|36.3307991|127.4417848|대전 동구 계족로 194-1|1</string>
    <string>행운복권방|-|37.6972007|126.6015352|경기 김포시 서암로 139 101호|1</string>
    <string>티켓몰|031-996-1112|37.6170038|126.7168485|경기 김포시 사우중로 15|1</string>
    <string>디즈니포토랜드|031-511-5417|37.6604201|127.2412475|경기 남양주시 늘을3로 11 호평동현대아이파크상가동 상가 117호, GS25호평아이파크점|1</string>
    <string>위드유로또|-|37.2187743|127.0602167|경기 화성시 동탄하나1길 61 109호|1</string>
    <string>바른손(퇴계점)|033-261-9638|37.8577538|127.7363901|강원 춘천시 퇴계로 168 주공2단지상가101호|1</string>
    <string>로또천국건천점|054-751-0300|35.8491887|129.1033309|경북 경주시 건천읍 내서로 1118,(건천리)|1</string>
    <string>나이스정보|-|35.4165377|129.1741607|경남 양산시 연호로 46 복권판매점|1</string>
    <string>넝쿨째(블루25 중앙점)|055-221-5128|35.1099624|128.5835707|경남 창원시 마산합포구 구산로 90 1층|1</string>
    <string>넝쿨째(블루25 중앙점)|055-221-5128|35.1099624|128.5835707|경남 창원시 마산합포구 구산로 90 1층|1</string>
    <string>넝쿨째(블루25 중앙점)|055-221-5128|35.1099624|128.5835707|경남 창원시 마산합포구 구산로 90 1층|1</string>
    <string>행복공간|02-483-2143|37.5320797|127.125094|서울 강동구 풍성로 115|2</string>
    <string>복권명당|02-484-4011|37.540278|127.1283386|서울 강동구 구천면로 214|2</string>
    <string>신명|02-2663-6500|37.5624103|126.8084515|서울 강서구 방화동로3길 1|2</string>
    <string>가판점|02-973-8951|37.6562713|127.0624069|서울 노원구 동일로 1231-2|2</string>
    <string>럭키복권방|-|37.6530492|127.0462877|서울 도봉구 노해로63길 79 우림빌딩106|2</string>
    <string>선일상회|-|37.5904467|127.0550711|서울 동대문구 회기로 171 1층|2</string>
    <string>종합가판점|02-959-5686|37.5803953|127.0379534|서울 동대문구 왕산로 206-2 청량리역 4번출구 가판점|2</string>
    <string>오케이상사|02-6282-2312|37.5038594|127.0033439|서울 서초구 신반포로 176 센트럴시티내100호매점|2</string>
    <string>로또복권판매소|02-2294-4262|37.56437469999999|127.0329317|서울 성동구 왕십리로26길 10,(도선동)|2</string>
    <string>복권천국|02-463-5050|37.5456902|127.0538371|서울 성동구 성수일로8길 30 1층|2</string>
    <string>영광정보통신|02-911-5016|37.6026597|127.0424818|서울 성북구 화랑로 92 1층 우측1호|2</string>
    <string>다모아복권|02-843-3332|37.4997846|126.9163465|서울 영등포구 신풍로 92 103호|2</string>
    <string>가판점(신문)|02-2636-6177|37.5344336|126.901288|서울 영등포구 양평로 48|2</string>
    <string>이촌가판점|02-749-5636|37.5207574|126.9734658|서울 용산구 이촌로71길 10|2</string>
    <string>중구-가로가판대-37|02-773-8798|37.5619687|126.9803334|서울 중구 남대문로 20-2,(남대문로3가)|2</string>
    <string>GS25(용마산역점)|02-494-2924|37.5751108|127.0852449|서울 중랑구 면목동 372-20번지|2</string>
    <string>파워24당감점|-|35.1550464|129.036378|부산 부산진구 가야대로589번길 3 1층|2</string>
    <string>가락하단|051-202-0449|35.1088292|128.9590703|부산 사하구 하단동 885-9번지 세븐일레븐|2</string>
    <string>만구수산유통|051-253-3573|35.0926611|129.0244828|부산 서구 남부민동 685번지 현대타운상가1층86호 복권판매점|2</string>
    <string>복권명당|053-634-6586|35.7982758|128.4955268|대구 달성군 화원읍 명곡리 105-1번지 102호|2</string>
    <string>대박마트|032-466-0746|37.4025779|126.7095559|인천 남동구 호구포로 219 세중프라자1층101-2호|2</string>
    <string>오천억복권방|062-363-1471|35.1529526|126.8807505|광주 서구 상무대로 1087|2</string>
    <string>모아스토아|042-535-8752|36.3445911|127.3683236|대전 서구 신갈마로 123|2</string>
    <string>이마트24 유성코아점|042-823-2870|36.3574433|127.338108|대전 유성구 문화원로6번길 103 코아마트|2</string>
    <string>GS25(대전태평점)|042-527-2534|36.3225485|127.3987458|대전 중구 유천동(유천2동) 189-5 백강미소빌딩|2</string>
    <string>삼산현대 로또판매|052-264-7110|35.5469048|129.3293925|울산 남구 월평로 225|2</string>
    <string>미보라복권방|052-293-0442|35.5593712|129.34325|울산 중구 염포로 15|2</string>
    <string>복드림로또방|-|35.5576413|129.3024522|울산 중구 유곡로 70|2</string>
    <string>마두5번출구가판로또|-|37.653848|126.7770976|경기 고양시 일산동구 중앙로 1200|2</string>
    <string>GS25(하안연서점)|02-806-7696|37.46552430000001|126.8774687|경기 광명시 안현로 52|2</string>
    <string>나이키로또복권방|031-761-1755|37.3628778|127.3131553|경기 광주시 경충대로 899 1층 111-1호(초월프라자)|2</string>
    <string>GS25(구리공원점)|031-568-2672|37.586709|127.1397735|경기 구리시 수택동 876번지|2</string>
    <string>패밀리복권방|-|37.6544528|127.244086|경기 남양주시 늘을2로 20 CH리베로원 103호|2</string>
    <string>패밀리복권방|-|37.6544528|127.244086|경기 남양주시 늘을2로 20 CH리베로원 103호|2</string>
    <string>대박|070-7643-4388|37.4881977|126.8116441|경기 부천시 지봉로 114 1층|2</string>
    <string>사랑방로또|032-323-4277|37.5025112|126.7715748|경기 부천시 원미구 중동 1147-5번지 cu중동설레임점 내|2</string>
    <string>굿투데이|070-8828-1212|37.3652839|127.107657|경기 성남시 분당구 성남대로331번길 3-3 110호 (정자동, 젤존타워3)|2</string>
    <string>둘리복권|-|37.35021649999999|126.7434858|경기 시흥시 다솜마을2길 33 102호|2</string>
    <string>진수아로또|031-416-0645|37.2875162|126.864064|경기 안산시 상록구 샘골로 40 102호|2</string>
    <string>천하명당복권방|031-674-8267|37.0065443|127.2737028|경기 안성시 중앙로 424|2</string>
    <string>GS25(동천현대점)|031-266-3321|37.3389579|127.0944355|경기 용인시 수지구 동천동 351|2</string>
    <string>희망을주는사람|031-338-5933|37.234639|127.2805173|경기 용인시 처인구 양지로 111 1층 상가|2</string>
    <string>노다지복권방|031-336-5781|37.2349979|127.2105432|경기 용인시 처인구 금령로 130,(마평동)|2</string>
    <string>노다지복권방|031-958-7136|37.8514077|126.8751499|경기 파주시 술이홀로 906|2</string>
    <string>희망복권|031-618-1742|36.9941768|127.0892717|경기 평택시 평택1로20번길 39 1층 복권방|2</string>
    <string>훼미리마트|031-535-5944|37.8989027|127.205013|경기 포천시 중앙로 148 신읍동|2</string>
    <string>로뎀|031-232-4215|37.2116472|126.8555023|경기 화성시 주석로 237|2</string>
    <string>1등로또|-|37.199327|127.0970177|경기 화성시 동탄대로14길 5-33 101호|2</string>
    <string>대박상사|031-356-3375|37.16169|126.707052|경기 화성시 궁평항로 1646-1 1층|2</string>
    <string>프로토원주점(복권나라)|033-745-8335|37.3850424|127.9479127|강원 원주시 북원로 2706 1층|2</string>
    <string>만사형통복권방|043-847-9007|36.9845288|127.939761|충북 충주시 연수동 1609 103동 2호|2</string>
    <string>송악로또복권판매점|-|36.8993015|126.6982587|충남 당진시 서해로 6431|2</string>
    <string>현대로또판매점|-|36.7775296|126.4642719|충남 서산시 율지5로 16|2</string>
    <string>행운로또판매점|041-548-1748|36.77393259999999|127.0713494|충남 아산시 북수로 97|2</string>
    <string>로또복권|-|36.7771359|127.0815262|충남 아산시 온천대로 2240 101호|2</string>
    <string>로또명당|041-522-8877|36.758491|127.1711428|충남 천안시 동남구 천안대로 103 5호|2</string>
    <string>G(금정)마트휴게실|-|35.9698653|126.7380723|전북 군산시 조촌로 66|2</string>
    <string>모래내마트|063-254-8818|35.833051|127.1424663|전북 전주시 덕진구 금암2동 200-13번지|2</string>
    <string>다사랑복권|063-909-0440|35.815059|127.1183993|전북 전주시 완산구 중화산로 54 1층|2</string>
    <string>복권방|053-854-0893|35.818817|128.822139|경북 경산시 자인면 서부리 148-1번지|2</string>
    <string>KOREA마트|054-458-9717|36.1204855|128.3522736|경북 구미시 구미중앙로42길 7|2</string>
    <string>파워할인마트|054-433-8484|36.1197322|128.1268538|경북 김천시 자산로 44-2 1층 파워할인마트내|2</string>
    <string>NG24|054-977-2555|36.0798033|128.4118396|경북 칠곡군 북중리3길 59|2</string>
    <string>목화휴게소|055-835-2780|35.0016472|128.0540468|경남 사천시 사천대로 912|2</string>
    <string>GS25(양산덕계점)|055-388-3816|35.375226|129.1519184|경남 양산시 덕계동 925번지|2</string>
    <string>완월로또|055-245-0671|35.1973464|128.5618808|경남 창원시 마산합포구 고운로 175 한미초록빌라 세븐일레븐 내|2</string>
    <string>중리복권|-|35.2509076|128.5108205|경남 창원시 마산회원구 내서읍 중리 976-2 1층|2</string>
    <string>GS25(창원극동점)|055-251-5780|35.2550061|128.6124402|경남 창원시 의창구 팔용동(팔룡동) 104-1 GS25편의점|2</string>
    <string>아리랑마트|055-543-6236|35.1496042|128.697718|경남 창원시 진해구 충장로 438|2</string>
    <string>환타지아복권방|064-722-2737|33.488394|126.5976166|제주 제주시 번영로 532|2</string>
</result>
