<?xml version="1.0" encoding="UTF-8"?>
<result>
    <string>바이드|051-862-7391|35.1839629|129.0824375|부산 연제구 연산동 710-1번지 세븐일레븐연산점 내|1</string>
    <string>차밍복권방|062-956-3366|35.1756019|126.8116101|광주 광산구 풍영로 41 동구빌딩1층|1</string>
    <string>영화유통(1등복권방)|052-269-9851|35.5338415|129.3221564|울산 남구 신정로 19 삼성아파트 상가 204-101|1</string>
    <string>일산탑복권|031-914-7575|37.6763665|126.7699582|경기 고양시 일산서구 일산로 517 107호|1</string>
    <string>CU(정동진모래시계점)|033-643-5137|37.6892008|129.0243271|강원 강릉시 강동면 정동진리 3-2번지|1</string>
    <string>복권명당|-|36.8380443|127.0738844|충남 아산시 음봉로 582|1</string>
    <string>무지개|063-468-3654|35.9622968|126.7145701|전북 군산시 수송남로 36-1|1</string>
    <string>로또복권애니타임점|054-476-8130|36.1090155|128.4200136|경북 구미시 인동중앙로11길 24 애니타임편의점 내|1</string>
    <string>복돼지복권방|02-497-5412|37.5486111|127.0558292|서울 성동구 아차산로7길 42|2</string>
    <string>종합가판제141호|02-2236-5931|37.5659102|127.0217363|서울 중구 퇴계로 447 황학 아크로타워|2</string>
    <string>축복마트|02-437-1813|37.5853624|127.0800776|서울 중랑구 동일로 616|2</string>
    <string>해피타임25|-|35.1108147|128.8785908|부산 강서구 화전산단4로6번길 6 101호|2</string>
    <string>아이앤지여고점 복권방|051-504-8730|35.1983474|129.0705523|부산 동래구 사직동 134-1번지|2</string>
    <string>SEVEN스토아|051-527-1777|35.20389979999999|129.1330064|부산 해운대구 반여동(반여제1동) 1441-125|2</string>
    <string>대박로또방|032-886-8889|37.4532497|126.6360578|인천 미추홀구 낙섬서로 46|2</string>
    <string>노다지복권방|042-638-4588|36.3743672|127.427155|대전 대덕구 아리랑로 213 대영상가 1층|2</string>
    <string>장터슈퍼|042-272-1654|36.319721|127.4385283|대전 동구 대전로 663-2,(인동)|2</string>
    <string>씨스페이스(유성봉명)|042-824-0535|36.3545719|127.3464496|대전 유성구 봉명동 546-4번지|2</string>
    <string>아이러브마트복권방|052-246-9901|35.5563674|129.3072327|울산 중구 유곡로 19-1|2</string>
    <string>로또명당|052-212-8949|35.5719599|129.3462942|울산 중구 병영로 28-1 1층, 부동산|2</string>
    <string>로또월드|031-976-7575|37.6849882|126.7771545|경기 고양시 일산서구 일산동 555-1번지 에이스빌딩116|2</string>
    <string>로또복권방|-|37.3592139|126.9323628|경기 군포시 산본로323번길 16-6 신명타워 신명빌딩1층1005호|2</string>
    <string>씨지랜드|032-325-5151|37.4900781|126.7534098|경기 부천시 송내대로73번길 11 금강리빙스텔111|2</string>
    <string>애리지|031-781-4557|37.4116217|127.1263444|경기 성남시 분당구 야탑로69번길 21|2</string>
    <string>구시청가판점|031-754-3336|37.4436876|127.1401772|경기 성남시 수정구 수정로 183|2</string>
    <string>플러스복권|-|37.3411254|126.7527288|경기 시흥시 큰솔로 42 102호|2</string>
    <string>아이지에이(IGA) 신길점|-|37.3343737|126.788131|경기 안산시 단원구 신길로 9-4|2</string>
    <string>가판대|031-441-3865|37.39279|126.9259848|경기 안양시 만안구 안양동 456-2번지|2</string>
    <string>대박복권방|031-855-8560|37.8224607|126.9867149|경기 양주시 가래비길 33|2</string>
    <string>복권나라|031-377-1589|37.1512188|127.0714738|경기 오산시 성호대로93번길 27|2</string>
    <string>행복로또|031-333-0067|37.3473485|127.2512456|경기 용인시 처인구 모현면 왕산리 743-5 101호|2</string>
    <string>교하복권판매점|031-8070-8055|37.7261202|126.7182498|경기 파주시 파주로 266 아이비타워108호|2</string>
    <string>행운나눔로또방|031-352-3124|37.1119594|126.9133743|경기 화성시 향남읍 하길리 1459-5|2</string>
    <string>황금로또|033-732-4477|37.3819545|127.9503291|강원 원주시 현충로318번길 35 1층|2</string>
    <string>대일마켓|043-836-4312|36.7829212|127.5828331|충북 증평군 증평읍 광장로 92,(중동리)|2</string>
    <string>월드마트|043-274-4578|36.6247627|127.4476935|충북 청주시 흥덕구 장구봉로129번길 2,(복대동)|2</string>
    <string>대박로또|041-956-7710|36.0109869|126.6954928|충남 서천군 장항로 160-1 임치과의원|2</string>
    <string>팡팡복권마트.잡화슈퍼|063-251-7764|35.8343875|127.1333902|전북 전주시 덕진구 가리내로 26|2</string>
    <string>토마토 오룡점|-|34.8118619|126.4703764|전남 무안군 삼향읍 남악리 1552 1층|2</string>
    <string>왕대박복권방|054-556-6404|36.6003182|128.188325|경북 문경시 중앙로 15,(모전동)|2</string>
    <string>AM&amp;PM|055-327-4867|35.2303561|128.8819013|경남 김해시 가락로 43 복권판매점|2</string>
    <string>무진장로또|064-755-0071|33.5136957|126.5270964|제주 제주시 일도일동(일도1동) 1047-4|2</string>
</result>
